Workbook
Name Slicer_Age_Group: #N/A
Name Slicer_Category: #N/A
Name Slicer_Discount_Group: #N/A
Name Slicer_Year: #N/A

Sheet products 
A1: Product ID | B1: Category | C1: Sub-category | D1: Product Name | E1: Brand Name | F1: Size | G1: Color | H1: Ratings
A2: P0001 | B2: Women | C2: Topwear | D2: T-Shirts | E2: Roadster | F2: 40 | G2: Black | H2: 4
A3: P0002 | B3: Women | C3: Topwear | D3: T-Shirts | E3: Roadster | F3: 40 | G3: Blue | H3: 5
A4: P0003 | B4: Women | C4: Topwear | D4: T-Shirts | E4: Roadster | F4: 42 | G4: White | H4: 3
A5: P0004 | B5: Women | C5: Topwear | D5: T-Shirts | E5: Roadster | F5: 44 | G5: Green | H5: 2
A6: P0005 | B6: Women | C6: Topwear | D6: T-Shirts | E6: Puma | F6: 38 | G6: Olive | H6: 5
A7: P0006 | B7: Women | C7: Topwear | D7: T-Shirts | E7: Puma | F7: 46 | G7: Pink | H7: 4
A8: P0007 | B8: Women | C8: Topwear | D8: T-Shirts | E8: Puma | F8: 38 | G8: Orange | H8: 3
A9: P0008 | B9: Women | C9: Topwear | D9: T-Shirts | E9: Puma | F9: 38 | G9: Beige | H9: 5
A10: P0009 | B10: Women | C10: Topwear | D10: T-Shirts | E10: Puma | F10: 38 | G10: Off white | H10: 4
A11: P0010 | B11: Women | C11: Topwear | D11: T-Shirts | E11: Puma | F11: 38 | G11: Purple | H11: 2
A12: P0011 | B12: Women | C12: Topwear | D12: T-Shirts | E12: Puma | F12: 38 | G12: Peach | H12: 5
A13: P0012 | B13: Women | C13: Topwear | D13: T-Shirts | E13: Puma | F13: 42 | G13: Sea Green | H13: 5
... A841: P0840 | B841: Men | C841: Bottomwear | D841: Pants | E841: Jockey | F841: 36 | G841: Orange | H841: 3
A842: P0841 | B842: Men | C842: Footwear | D842: Casual Shoes | E842: Puma | F842: 6 UK | G842: Green | H842: 5
A843: P0842 | B843: Men | C843: Footwear | D843: Casual Shoes | E843: Puma | F843: 7 UK | G843: Purple | H843: 5
A844: P0843 | B844: Men | C844: Footwear | D844: Casual Shoes | E844: Puma | F844: 8 UK | G844: White | H844: 4
A845: P0844 | B845: Men | C845: Footwear | D845: Casual Shoes | E845: Puma | F845: 9 UK | G845: Off white | H845: 3
A846: P0845 | B846: Men | C846: Footwear | D846: Casual Shoes | E846: Puma | F846: 10 UK | G846: Off white | H846: 3
A847: P0846 | B847: Men | C847: Footwear | D847: Casual Shoes | E847: Puma | F847: 11 UK | G847: Off white | H847: 5
A848: P0847 | B848: Men | C848: Footwear | D848: Casual Shoes | E848: Puma | F848: 11 UK | G848: Off white | H848: 5
A849: P0848 | B849: Men | C849: Footwear | D849: Casual Shoes | E849: Puma | F849: 11 UK | G849: Off white | H849: 4
A850: P0849 | B850: Men | C850: Footwear | D850: Casual Shoes | E850: Puma | F850: 11 UK | G850: Off white | H850: 2
A851: P0850 | B851: Men | C851: Footwear | D851: Casual Shoes | E851: Puma | F851: 11 UK | G851: Off white | H851: 3
A852: P0851 | B852: Men | C852: Footwear | D852: Casual Shoes | E852: Puma | F852: 11 UK | G852: Off white | H852: 4
A853: P0852 | B853: Men | C853: Footwear | D853: Casual Shoes | E853: Puma | F853: 11 UK | G853: Off white | H853: 5
... A1463: P1462 | B1463: Women | C1463: Western Wear | D1463: T-Shirts | E1463: ONLY | F1463: M | G1463: Pink | H1463: 4
A1464: P1463 | B1464: Women | C1464: Western Wear | D1464: Jeans | E1464: Roadster | F1464: 30 | G1464: Pink | H1464: 2
A1465: P1464 | B1465: Women | C1465: Western Wear | D1465: Jeans | E1465: Roadster | F1465: 30 | G1465: Pink | H1465: 5
A1466: P1465 | B1466: Women | C1466: Western Wear | D1466: Jeans | E1466: Roadster | F1466: 30 | G1466: Pink | H1466: 5
A1467: P1466 | B1467: Women | C1467: Western Wear | D1467: Jeans | E1467: Roadster | F1467: 30 | G1467: Pink | H1467: 4
A1468: P1467 | B1468: Women | C1468: Western Wear | D1468: Jeans | E1468: Roadster | F1468: 30 | G1468: Pink | H1468: 4
A1469: P1468 | B1469: Women | C1469: Western Wear | D1469: Jeans | E1469: Roadster | F1469: 30 | G1469: Pink | H1469: 4
A1470: P1469 | B1470: Women | C1470: Western Wear | D1470: Jeans | E1470: Roadster | F1470: 30 | G1470: Blue | H1470: 3
A1471: P1470 | B1471: Women | C1471: Western Wear | D1471: Jeans | E1471: Roadster | F1471: 30 | G1471: Blue | H1471: 5
A1472: P1471 | B1472: Women | C1472: Western Wear | D1472: Jeans | E1472: Roadster | F1472: 32 | G1472: Blue | H1472: 4
A1473: P1472 | B1473: Women | C1473: Western Wear | D1473: Jeans | E1473: Roadster | F1473: 32 | G1473: Navy Blue | H1473: 2
A1474: P1473 | B1474: Women | C1474: Western Wear | D1474: Jeans | E1474: Roadster | F1474: 32 | G1474: Navy Blue | H1474: 5
A1475: P1474 | B1475: Women | C1475: Western Wear | D1475: Jeans | E1475: Roadster | F1475: 32 | G1475: Navy Blue | H1475: 5
... A1588: P1587 | B1588: Women | C1588: Western Wear | D1588: Jeans | E1588: Allen Solly | F1588: 30 | G1588: Khaki | H1588: 4
A1589: P1588 | B1589: Women | C1589: Western Wear | D1589: Jumpsuits | E1589: Allen Solly | F1589: S | G1589: Khaki | H1589: 4
A1590: P1589 | B1590: Women | C1590: Western Wear | D1590: Jumpsuits | E1590: Allen Solly | F1590: S | G1590: Skin | H1590: 5
A1591: P1590 | B1591: Women | C1591: Western Wear | D1591: Jumpsuits | E1591: Allen Solly | F1591: S | G1591: Skin | H1591: 5
A1592: P1591 | B1592: Women | C1592: Western Wear | D1592: Jumpsuits | E1592: Allen Solly | F1592: S | G1592: Lavender | H1592: 3
A1593: P1592 | B1593: Women | C1593: Western Wear | D1593: Jumpsuits | E1593: Allen Solly | F1593: S | G1593: Black | H1593: 5
A1594: P1593 | B1594: Women | C1594: Western Wear | D1594: Jumpsuits | E1594: Allen Solly | F1594: S | G1594: Sea Green | H1594: 5
A1595: P1594 | B1595: Women | C1595: Western Wear | D1595: Jumpsuits | E1595: Allen Solly | F1595: S | G1595: Lavender | H1595: 4
A1596: P1595 | B1596: Women | C1596: Western Wear | D1596: Jumpsuits | E1596: Allen Solly | F1596: M | G1596: Black | H1596: 3
A1597: P1596 | B1597: Women | C1597: Western Wear | D1597: Jumpsuits | E1597: Allen Solly | F1597: M | G1597: Blue | H1597: 5
A1598: P1597 | B1598: Women | C1598: Western Wear | D1598: Jumpsuits | E1598: Allen Solly | F1598: M | G1598: White | H1598: 4
A1599: P1598 | B1599: Women | C1599: Western Wear | D1599: Jumpsuits | E1599: Allen Solly | F1599: M | G1599: Green | H1599: 3
A1600: P1599 | B1600: Women | C1600: Western Wear | D1600: Jumpsuits | E1600: Allen Solly | F1600: M | G1600: Black | H1600: 5
... A1658: P1657 | B1658: Women | C1658: Western Wear | D1658: Jumpsuits | E1658: Mayra | F1658: XL | G1658: Pink | H1658: 5
A1659: P1658 | B1659: Women | C1659: Western Wear | D1659: Shorts | E1659: H&M | F1659: 26 | G1659: Pink | H1659: 4
A1660: P1659 | B1660: Women | C1660: Western Wear | D1660: Shorts | E1660: H&M | F1660: 26 | G1660: Pink | H1660: 4
A1661: P1660 | B1661: Women | C1661: Western Wear | D1661: Shorts | E1661: H&M | F1661: 26 | G1661: Pink | H1661: 4
A1662: P1661 | B1662: Women | C1662: Western Wear | D1662: Shorts | E1662: H&M | F1662: 26 | G1662: Black | H1662: 5
A1663: P1662 | B1663: Women | C1663: Western Wear | D1663: Shorts | E1663: H&M | F1663: 26 | G1663: Beige | H1663: 5
A1664: P1663 | B1664: Women | C1664: Western Wear | D1664: Shorts | E1664: H&M | F1664: 26 | G1664: Beige | H1664: 3
A1665: P1664 | B1665: Women | C1665: Western Wear | D1665: Shorts | E1665: H&M | F1665: 26 | G1665: Beige | H1665: 5
A1666: P1665 | B1666: Women | C1666: Western Wear | D1666: Shorts | E1666: H&M | F1666: 26 | G1666: Beige | H1666: 5
A1667: P1666 | B1667: Women | C1667: Western Wear | D1667: Shorts | E1667: H&M | F1667: 26 | G1667: Beige | H1667: 4
A1668: P1667 | B1668: Women | C1668: Western Wear | D1668: Shorts | E1668: H&M | F1668: 26 | G1668: Beige | H1668: 3
A1669: P1668 | B1669: Women | C1669: Western Wear | D1669: Shorts | E1669: H&M | F1669: 28 | G1669: Beige | H1669: 5
A1670: P1669 | B1670: Women | C1670: Western Wear | D1670: Shorts | E1670: H&M | F1670: 28 | G1670: Beige | H1670: 4
... A1742: P1741 | B1742: Women | C1742: Western Wear | D1742: Shorts | E1742: DressBerry | F1742: 34 | G1742: Teal | H1742: 3
A1743: P1742 | B1743: Women | C1743: Footwear | D1743: Flats | E1743: Bata | F1743: 6 UK | G1743: Teal | H1743: 5
A1744: P1743 | B1744: Women | C1744: Footwear | D1744: Flats | E1744: Bata | F1744: 7 UK | G1744: Teal | H1744: 5
A1745: P1744 | B1745: Women | C1745: Footwear | D1745: Flats | E1745: Bata | F1745: 8 UK | G1745: Teal | H1745: 4
A1746: P1745 | B1746: Women | C1746: Footwear | D1746: Flats | E1746: Bata | F1746: 9 UK | G1746: Sea Green | H1746: 3
A1747: P1746 | B1747: Women | C1747: Footwear | D1747: Flats | E1747: Bata | F1747: 10 UK | G1747: Red | H1747: 4
A1748: P1747 | B1748: Women | C1748: Footwear | D1748: Flats | E1748: Bata | F1748: 11 UK | G1748: Blue | H1748: 5
A1749: P1748 | B1749: Women | C1749: Footwear | D1749: Flats | E1749: Bata | F1749: 11 UK | G1749: Orange | H1749: 3
A1750: P1749 | B1750: Women | C1750: Footwear | D1750: Flats | E1750: Bata | F1750: 11 UK | G1750: Green | H1750: 2
A1751: P1750 | B1751: Women | C1751: Footwear | D1751: Flats | E1751: Bata | F1751: 11 UK | G1751: Purple | H1751: 5
A1752: P1751 | B1752: Women | C1752: Footwear | D1752: Flats | E1752: Bata | F1752: 11 UK | G1752: White | H1752: 4
A1753: P1752 | B1753: Women | C1753: Footwear | D1753: Flats | E1753: Bata | F1753: 11 UK | G1753: Off white | H1753: 3
A1754: P1753 | B1754: Women | C1754: Footwear | D1754: Flats | E1754: Bata | F1754: 11 UK | G1754: Sea Green | H1754: 5
... A3072: P3071 | B3072: Kids | C3072: Footwear | D3072: Sandals | E3072: Campus | F3072: 3-6M | G3072: Charcoal | H3072: 4

Sheet customers
A1: Customer ID | B1: Customer Age | C1: City | D1: State
A2: C001 | B2: 30 | C2: Mumbai | D2: Maharashtra
A3: C002 | B3: 35 | C3: Mumbai | D3: Maharashtra
A4: C003 | B4: 36 | C4: Mumbai | D4: Maharashtra
A5: C004 | B5: 40 | C5: Pune | D5: Maharashtra
A6: C005 | B6: 25 | C6: Pune | D6: Maharashtra
A7: C006 | B7: 16 | C7: Pune | D7: Maharashtra
A8: C007 | B8: 23 | C8: Pune | D8: Maharashtra
A9: C008 | B9: 22 | C9: Pune | D9: Maharashtra
A10: C009 | B10: 17 | C10: Hyderabad | D10: Telangana
A11: C010 | B11: 19 | C11: Hyderabad | D11: Telangana
A12: C011 | B12: 18 | C12: Hyderabad | D12: Telangana
A13: C012 | B13: 20 | C13: Hyderabad | D13: Telangana
... A101: C100 | B101: 40 | C101: Udaipur | D101: Rajasthan

Sheet fact_orders
A1: Order ID | B1: Customer ID | C1: Product ID | D1: Date | E1: Original Price | F1: Discount%
A2: OD0001 | B2: C001 | C2: P0001 | D2: =RANDBETWEEN(DATE(2021,1,1),DATE(2023,3,31)) -> 44645 | E2: 349 | F2: 0.3
A3: OD0002 | B3: C002 | C3: P0001 | D3: =RANDBETWEEN(DATE(2021,1,1),DATE(2023,3,31)) -> 44372 | E3: 350 | F3: 0.3
A4: OD0003 | B4: C003 | C4: P0001 | D4: =RANDBETWEEN(DATE(2021,1,1),DATE(2023,3,31)) -> 44936 | E4: 351 | F4: 0.3
A5: OD0004 | B5: C004 | C5: P0001 | D5: =RANDBETWEEN(DATE(2021,1,1),DATE(2023,3,31)) -> 44976 | E5: 352 | F5: 0.25
A6: OD0005 | B6: C005 | C6: P0001 | D6: =RANDBETWEEN(DATE(2021,1,1),DATE(2023,3,31)) -> 44460 | E6: 353 | F6: 0.25
A7: OD0006 | B7: C006 | C7: P0002 | D7: =RANDBETWEEN(DATE(2021,1,1),DATE(2023,3,31)) -> 44601 | E7: 354 | F7: 0.3
A8: OD0007 | B8: C007 | C8: P0003 | D8: =RANDBETWEEN(DATE(2021,1,1),DATE(2023,3,31)) -> 44642 | E8: 355 | F8: 0.3
A9: OD0008 | B9: C008 | C9: P0004 | D9: =RANDBETWEEN(DATE(2021,1,1),DATE(2023,3,31)) -> 44640 | E9: 356 | F9: 0.3
A10: OD0009 | B10: C009 | C10: P0005 | D10: =RANDBETWEEN(DATE(2021,1,1),DATE(2023,3,31)) -> 44366 | E10: 2222 | F10: 0.4
A11: OD0010 | B11: C010 | C11: P0006 | D11: =RANDBETWEEN(DATE(2021,1,1),DATE(2023,3,31)) -> 44807 | E11: 2342 | F11: 0.4
A12: OD0011 | B12: C011 | C12: P0007 | D12: =RANDBETWEEN(DATE(2021,1,1),DATE(2023,3,31)) -> 44713 | E12: 2241 | F12: 0.4
A13: OD0012 | B13: C012 | C13: P0007 | D13: =RANDBETWEEN(DATE(2021,1,1),DATE(2023,3,31)) -> 44243 | E13: 2253 | F13: 0.4
... A3072: OD3071 | B3072: C056 | C3072: P2711 | D3072: =RANDBETWEEN(DATE(2021,1,1),DATE(2023,3,31)) -> 44388 | E3072: 555 | F3072: 0.25
A3073: OD3072 | B3073: C057 | C3073: P2712 | D3073: =RANDBETWEEN(DATE(2021,1,1),DATE(2023,3,31)) -> 44676 | E3073: =RANDBETWEEN(600, 2000) -> 986 | F3073: 0.3
A3074: OD3073 | B3074: C058 | C3074: P2713 | D3074: =RANDBETWEEN(DATE(2021,1,1),DATE(2023,3,31)) -> 44650 | E3074: =RANDBETWEEN(600, 2000) -> 1778 | F3074: 0.3
A3075: OD3074 | B3075: C059 | C3075: P2714 | D3075: =RANDBETWEEN(DATE(2021,1,1),DATE(2023,3,31)) -> 44786 | E3075: =RANDBETWEEN(600, 2000) -> 1175 | F3075: 0.3
A3076: OD3075 | B3076: C060 | C3076: P2715 | D3076: =RANDBETWEEN(DATE(2021,1,1),DATE(2023,3,31)) -> 44409 | E3076: =RANDBETWEEN(600, 2000) -> 1502 | F3076: 0.25
A3077: OD3076 | B3077: C061 | C3077: P2716 | D3077: =RANDBETWEEN(DATE(2021,1,1),DATE(2023,3,31)) -> 44980 | E3077: =RANDBETWEEN(600, 2000) -> 1187 | F3077: 0.25
A3078: OD3077 | B3078: C062 | C3078: P2717 | D3078: =RANDBETWEEN(DATE(2021,1,1),DATE(2023,3,31)) -> 44844 | E3078: =RANDBETWEEN(600, 2000) -> 1764 | F3078: 0.3
A3079: OD3078 | B3079: C063 | C3079: P2718 | D3079: =RANDBETWEEN(DATE(2021,1,1),DATE(2023,3,31)) -> 44826 | E3079: =RANDBETWEEN(600, 2000) -> 656 | F3079: 0.3
A3080: OD3079 | B3080: C064 | C3080: P2719 | D3080: =RANDBETWEEN(DATE(2021,1,1),DATE(2023,3,31)) -> 44950 | E3080: =RANDBETWEEN(600, 2000) -> 1367 | F3080: 0.3
A3081: OD3080 | B3081: C065 | C3081: P2720 | D3081: =RANDBETWEEN(DATE(2021,1,1),DATE(2023,3,31)) -> 44231 | E3081: =RANDBETWEEN(600, 2000) -> 712 | F3081: 0.4
A3082: OD3081 | B3082: C066 | C3082: P2721 | D3082: =RANDBETWEEN(DATE(2021,1,1),DATE(2023,3,31)) -> 44371 | E3082: =RANDBETWEEN(600, 2000) -> 1571 | F3082: 0.4
A3083: OD3082 | B3083: C067 | C3083: P2722 | D3083: =RANDBETWEEN(DATE(2021,1,1),DATE(2023,3,31)) -> 44563 | E3083: =RANDBETWEEN(600, 2000) -> 1828 | F3083: 0.4
A3084: OD3083 | B3084: C068 | C3084: P2723 | D3084: =RANDBETWEEN(DATE(2021,1,1),DATE(2023,3,31)) -> 44924 | E3084: =RANDBETWEEN(600, 2000) -> 743 | F3084: 0.4
... A3447: OD3446 | B3447: C031 | C3447: P3046 | D3447: =RANDBETWEEN(DATE(2021,1,1),DATE(2023,3,31)) -> 44477 | E3447: =RANDBETWEEN(600, 2000) -> 1934 | F3447: 0.39
A3448: OD3447 | B3448: C032 | C3448: P3047 | D3448: =RANDBETWEEN(DATE(2021,1,1),DATE(2023,3,31)) -> 44953 | E3448: 2245 | F3448: 0.39
A3449: OD3448 | B3449: C033 | C3449: P3048 | D3449: =RANDBETWEEN(DATE(2021,1,1),DATE(2023,3,31)) -> 44236 | E3449: 2354 | F3449: 0.39
A3450: OD3449 | B3450: C034 | C3450: P3049 | D3450: =RANDBETWEEN(DATE(2021,1,1),DATE(2023,3,31)) -> 44932 | E3450: 2214 | F3450: 0.39
A3451: OD3450 | B3451: C035 | C3451: P3050 | D3451: =RANDBETWEEN(DATE(2021,1,1),DATE(2023,3,31)) -> 44919 | E3451: 2365 | F3451: 0.3
A3452: OD3451 | B3452: C036 | C3452: P3051 | D3452: =RANDBETWEEN(DATE(2021,1,1),DATE(2023,3,31)) -> 44667 | E3452: 2541 | F3452: 0.3
A3453: OD3452 | B3453: C037 | C3453: P3052 | D3453: =RANDBETWEEN(DATE(2021,1,1),DATE(2023,3,31)) -> 44307 | E3453: 1235 | F3453: 0.3
A3454: OD3453 | B3454: C038 | C3454: P3053 | D3454: =RANDBETWEEN(DATE(2021,1,1),DATE(2023,3,31)) -> 44772 | E3454: 22365 | F3454: 0.25
A3455: OD3454 | B3455: C039 | C3455: P3054 | D3455: =RANDBETWEEN(DATE(2021,1,1),DATE(2023,3,31)) -> 44442 | E3455: 2245 | F3455: 0.25
A3456: OD3455 | B3456: C040 | C3456: P3054 | D3456: =RANDBETWEEN(DATE(2021,1,1),DATE(2023,3,31)) -> 44695 | E3456: 2245 | F3456: 0.3
A3457: OD3456 | B3457: C041 | C3457: P3054 | D3457: =RANDBETWEEN(DATE(2021,1,1),DATE(2023,3,31)) -> 44671 | E3457: 2542 | F3457: 0.3
A3458: OD3457 | B3458: C042 | C3458: P3054 | D3458: =RANDBETWEEN(DATE(2021,1,1),DATE(2023,3,31)) -> 44241 | E3458: 2263 | F3458: 0.3
A3459: OD3458 | B3459: C043 | C3459: P3054 | D3459: =RANDBETWEEN(DATE(2021,1,1),DATE(2023,3,31)) -> 44310 | E3459: 6523 | F3459: 0.4
... A3467: OD3466 | B3467: C051 | C3467: P3057 | D3467: =RANDBETWEEN(DATE(2021,1,1),DATE(2023,3,31)) -> 44359 | E3467: 4454 | F3467: 0.45
A3468: OD3467 | B3468: C052 | C3468: P3058 | D3468: =RANDBETWEEN(DATE(2021,1,1),DATE(2023,3,31)) -> 45000 | E3468: =RANDBETWEEN(600, 2000) -> 1099 | F3468: 0.47
A3469: OD3468 | B3469: C053 | C3469: P3059 | D3469: =RANDBETWEEN(DATE(2021,1,1),DATE(2023,3,31)) -> 44366 | E3469: =RANDBETWEEN(600, 2000) -> 1779 | F3469: 0.47
A3470: OD3469 | B3470: C054 | C3470: P3060 | D3470: =RANDBETWEEN(DATE(2021,1,1),DATE(2023,3,31)) -> 44324 | E3470: =RANDBETWEEN(600, 2000) -> 1619 | F3470: 0.46
A3471: OD3470 | B3471: C055 | C3471: P3061 | D3471: =RANDBETWEEN(DATE(2021,1,1),DATE(2023,3,31)) -> 44970 | E3471: =RANDBETWEEN(600, 2000) -> 941 | F3471: 0.46
A3472: OD3471 | B3472: C056 | C3472: P3062 | D3472: =RANDBETWEEN(DATE(2021,1,1),DATE(2023,3,31)) -> 44412 | E3472: =RANDBETWEEN(600, 2000) -> 1286 | F3472: 0.46
A3473: OD3472 | B3473: C057 | C3473: P3063 | D3473: =RANDBETWEEN(DATE(2021,1,1),DATE(2023,3,31)) -> 44335 | E3473: =RANDBETWEEN(600, 2000) -> 620 | F3473: 0.3
A3474: OD3473 | B3474: C058 | C3474: P3064 | D3474: =RANDBETWEEN(DATE(2021,1,1),DATE(2023,3,31)) -> 44262 | E3474: =RANDBETWEEN(600, 2000) -> 1609 | F3474: 0.3
A3475: OD3474 | B3475: C059 | C3475: P3065 | D3475: =RANDBETWEEN(DATE(2021,1,1),DATE(2023,3,31)) -> 44215 | E3475: =RANDBETWEEN(600, 2000) -> 879 | F3475: 0.3
A3476: OD3475 | B3476: C060 | C3476: P3066 | D3476: =RANDBETWEEN(DATE(2021,1,1),DATE(2023,3,31)) -> 44760 | E3476: =RANDBETWEEN(600, 2000) -> 1743 | F3476: 0.3
A3477: OD3476 | B3477: C061 | C3477: P3067 | D3477: =RANDBETWEEN(DATE(2021,1,1),DATE(2023,3,31)) -> 44270 | E3477: =RANDBETWEEN(600, 2000) -> 1907 | F3477: 0.3
A3478: OD3477 | B3478: C062 | C3478: P3068 | D3478: =RANDBETWEEN(DATE(2021,1,1),DATE(2023,3,31)) -> 44599 | E3478: =RANDBETWEEN(600, 2000) -> 1411 | F3478: 0.35
A3479: OD3478 | B3479: C063 | C3479: P3068 | D3479: =RANDBETWEEN(DATE(2021,1,1),DATE(2023,3,31)) -> 44814 | E3479: =RANDBETWEEN(600, 2000) -> 1820 | F3479: 0.35
... A3501: OD3500 | B3501: C085 | C3501: P3071 | D3501: =RANDBETWEEN(DATE(2021,1,1),DATE(2023,3,31)) -> 44858 | E3501: =RANDBETWEEN(600, 2000) -> 1749 | F3501: 0.5

Sheet Myntra Dataset
A1: Order ID | B1: Customer ID | C1: Product ID | D1: Date | E1: Month | F1: Year | G1: Original Price | H1: Discount | I1: Discount Group | J1: Revenue | K1: Age | L1: Age Group | M1: City | N1: State | O1: Category | P1: Sub-category | Q1: Product Name | R1: Brand Name | S1: Size | T1: Color | U1: Ratings
A2: OD0001 | B2: C001 | C2: P0001 | D2: =RANDBETWEEN(DATE(2021,1,1),DATE(2023,3,31)) -> 44873 | E2: =TEXT(Table1[[#This Row],[Date]],"mmm") -> Nov | F2: =TEXT(Table1[[#This Row],[Date]],"yyyy") -> 2022 | G2: 349 | H2: 0.3 | I2: {=_xlfn.IFS(Table1[[#This Row],[Discount]]<=0.2,"Low",Table1[[#This Row],[Discount]]<=0.4,"Medium",Table1[[#This Row],[Discount]]>0.4,"High")} -> Medium | J2: =Table1[[#This Row],[Original Price]]*(1-Table1[[#This Row],[Discount]]) -> 244.3 | K2: =VLOOKUP(B2,customers!$A$2:$D$101,2,0) -> 30 | L2: {=_xlfn.IFS(Table1[[#This Row],[Age]]<=12,"Kids",Table1[[#This Row],[Age]]<=19,"Teenage",Table1[[#This Row],[Age]]<=29,"Young Adult",Table1[[#This Row],[Age]]<=45,"Adult",Table1[[#This Row],[Age]]>=46,"Senior")} -> Adult | M2: =VLOOKUP(B2,customers!A$2:D$101,3,0) -> Mumbai | N2: =VLOOKUP(B2,customers!$A$2:$D$101,4,0) -> Maharashtra | O2: =VLOOKUP(C2,'products '!$A$2:$H$3072,2,0) -> Women | P2: =VLOOKUP(C2,'products '!$A$2:$H$3072,3,0) -> Topwear | Q2: =VLOOKUP(C2,'products '!$A$2:$H$3072,4,0) -> T-Shirts | R2: =VLOOKUP(C2,'products '!$A$2:$H$3072,5,0) -> Roadster | S2: =VLOOKUP(C2,'products '!$A$2:$H$3072,6,0) -> 40 | T2: =VLOOKUP(C2,'products '!$A$2:$H$3072,7,0) -> Black | U2: =VLOOKUP(C2,'products '!$A$2:$H$3072,8,0) -> 4
A3: OD0002 | B3: C002 | C3: P0001 | D3: =RANDBETWEEN(DATE(2021,1,1),DATE(2023,3,31)) -> 44464 | E3: =TEXT(Table1[[#This Row],[Date]],"mmm") -> Sep | F3: =TEXT(Table1[[#This Row],[Date]],"yyyy") -> 2021 | G3: 350 | H3: 0.3 | I3: {=_xlfn.IFS(Table1[[#This Row],[Discount]]<=0.2,"Low",Table1[[#This Row],[Discount]]<=0.4,"Medium",Table1[[#This Row],[Discount]]>0.4,"High")} -> Medium | J3: =Table1[[#This Row],[Original Price]]*(1-Table1[[#This Row],[Discount]]) -> 245 | K3: =VLOOKUP(B3,customers!$A$2:$D$101,2,0) -> 35 | L3: {=_xlfn.IFS(Table1[[#This Row],[Age]]<=12,"Kids",Table1[[#This Row],[Age]]<=19,"Teenage",Table1[[#This Row],[Age]]<=29,"Young Adult",Table1[[#This Row],[Age]]<=45,"Adult",Table1[[#This Row],[Age]]>=46,"Senior")} -> Adult | M3: =VLOOKUP(B3,customers!A$2:D$101,3,0) -> Mumbai | N3: =VLOOKUP(B3,customers!$A$2:$D$101,4,0) -> Maharashtra | O3: =VLOOKUP(C3,'products '!$A$2:$H$3072,2,0) -> Women | P3: =VLOOKUP(C3,'products '!$A$2:$H$3072,3,0) -> Topwear | Q3: =VLOOKUP(C3,'products '!$A$2:$H$3072,4,0) -> T-Shirts | R3: =VLOOKUP(C3,'products '!$A$2:$H$3072,5,0) -> Roadster | S3: =VLOOKUP(C3,'products '!$A$2:$H$3072,6,0) -> 40 | T3: =VLOOKUP(C3,'products '!$A$2:$H$3072,7,0) -> Black | U3: =VLOOKUP(C3,'products '!$A$2:$H$3072,8,0) -> 4
A4: OD0003 | B4: C003 | C4: P0001 | D4: =RANDBETWEEN(DATE(2021,1,1),DATE(2023,3,31)) -> 44444 | E4: =TEXT(Table1[[#This Row],[Date]],"mmm") -> Sep | F4: =TEXT(Table1[[#This Row],[Date]],"yyyy") -> 2021 | G4: 351 | H4: 0.3 | I4: {=_xlfn.IFS(Table1[[#This Row],[Discount]]<=0.2,"Low",Table1[[#This Row],[Discount]]<=0.4,"Medium",Table1[[#This Row],[Discount]]>0.4,"High")} -> Medium | J4: =Table1[[#This Row],[Original Price]]*(1-Table1[[#This Row],[Discount]]) -> 245.7 | K4: =VLOOKUP(B4,customers!$A$2:$D$101,2,0) -> 36 | L4: {=_xlfn.IFS(Table1[[#This Row],[Age]]<=12,"Kids",Table1[[#This Row],[Age]]<=19,"Teenage",Table1[[#This Row],[Age]]<=29,"Young Adult",Table1[[#This Row],[Age]]<=45,"Adult",Table1[[#This Row],[Age]]>=46,"Senior")} -> Adult | M4: =VLOOKUP(B4,customers!A$2:D$101,3,0) -> Mumbai | N4: =VLOOKUP(B4,customers!$A$2:$D$101,4,0) -> Maharashtra | O4: =VLOOKUP(C4,'products '!$A$2:$H$3072,2,0) -> Women | P4: =VLOOKUP(C4,'products '!$A$2:$H$3072,3,0) -> Topwear | Q4: =VLOOKUP(C4,'products '!$A$2:$H$3072,4,0) -> T-Shirts | R4: =VLOOKUP(C4,'products '!$A$2:$H$3072,5,0) -> Roadster | S4: =VLOOKUP(C4,'products '!$A$2:$H$3072,6,0) -> 40 | T4: =VLOOKUP(C4,'products '!$A$2:$H$3072,7,0) -> Black | U4: =VLOOKUP(C4,'products '!$A$2:$H$3072,8,0) -> 4
A5: OD0004 | B5: C004 | C5: P0001 | D5: =RANDBETWEEN(DATE(2021,1,1),DATE(2023,3,31)) -> 45007 | E5: =TEXT(Table1[[#This Row],[Date]],"mmm") -> Mar | F5: =TEXT(Table1[[#This Row],[Date]],"yyyy") -> 2023 | G5: 352 | H5: 0.25 | I5: {=_xlfn.IFS(Table1[[#This Row],[Discount]]<=0.2,"Low",Table1[[#This Row],[Discount]]<=0.4,"Medium",Table1[[#This Row],[Discount]]>0.4,"High")} -> Medium | J5: =Table1[[#This Row],[Original Price]]*(1-Table1[[#This Row],[Discount]]) -> 264 | K5: =VLOOKUP(B5,customers!$A$2:$D$101,2,0) -> 40 | L5: {=_xlfn.IFS(Table1[[#This Row],[Age]]<=12,"Kids",Table1[[#This Row],[Age]]<=19,"Teenage",Table1[[#This Row],[Age]]<=29,"Young Adult",Table1[[#This Row],[Age]]<=45,"Adult",Table1[[#This Row],[Age]]>=46,"Senior")} -> Adult | M5: =VLOOKUP(B5,customers!A$2:D$101,3,0) -> Pune | N5: =VLOOKUP(B5,customers!$A$2:$D$101,4,0) -> Maharashtra | O5: =VLOOKUP(C5,'products '!$A$2:$H$3072,2,0) -> Women | P5: =VLOOKUP(C5,'products '!$A$2:$H$3072,3,0) -> Topwear | Q5: =VLOOKUP(C5,'products '!$A$2:$H$3072,4,0) -> T-Shirts | R5: =VLOOKUP(C5,'products '!$A$2:$H$3072,5,0) -> Roadster | S5: =VLOOKUP(C5,'products '!$A$2:$H$3072,6,0) -> 40 | T5: =VLOOKUP(C5,'products '!$A$2:$H$3072,7,0) -> Black | U5: =VLOOKUP(C5,'products '!$A$2:$H$3072,8,0) -> 4
A6: OD0005 | B6: C005 | C6: P0001 | D6: =RANDBETWEEN(DATE(2021,1,1),DATE(2023,3,31)) -> 44785 | E6: =TEXT(Table1[[#This Row],[Date]],"mmm") -> Aug | F6: =TEXT(Table1[[#This Row],[Date]],"yyyy") -> 2022 | G6: 353 | H6: 0.25 | I6: {=_xlfn.IFS(Table1[[#This Row],[Discount]]<=0.2,"Low",Table1[[#This Row],[Discount]]<=0.4,"Medium",Table1[[#This Row],[Discount]]>0.4,"High")} -> Medium | J6: =Table1[[#This Row],[Original Price]]*(1-Table1[[#This Row],[Discount]]) -> 264.75 | K6: =VLOOKUP(B6,customers!$A$2:$D$101,2,0) -> 25 | L6: {=_xlfn.IFS(Table1[[#This Row],[Age]]<=12,"Kids",Table1[[#This Row],[Age]]<=19,"Teenage",Table1[[#This Row],[Age]]<=29,"Young Adult",Table1[[#This Row],[Age]]<=45,"Adult",Table1[[#This Row],[Age]]>=46,"Senior")} -> Young Adult | M6: =VLOOKUP(B6,customers!A$2:D$101,3,0) -> Pune | N6: =VLOOKUP(B6,customers!$A$2:$D$101,4,0) -> Maharashtra | O6: =VLOOKUP(C6,'products '!$A$2:$H$3072,2,0) -> Women | P6: =VLOOKUP(C6,'products '!$A$2:$H$3072,3,0) -> Topwear | Q6: =VLOOKUP(C6,'products '!$A$2:$H$3072,4,0) -> T-Shirts | R6: =VLOOKUP(C6,'products '!$A$2:$H$3072,5,0) -> Roadster | S6: =VLOOKUP(C6,'products '!$A$2:$H$3072,6,0) -> 40 | T6: =VLOOKUP(C6,'products '!$A$2:$H$3072,7,0) -> Black | U6: =VLOOKUP(C6,'products '!$A$2:$H$3072,8,0) -> 4
A7: OD0006 | B7: C006 | C7: P0002 | D7: =RANDBETWEEN(DATE(2021,1,1),DATE(2023,3,31)) -> 44943 | E7: =TEXT(Table1[[#This Row],[Date]],"mmm") -> Jan | F7: =TEXT(Table1[[#This Row],[Date]],"yyyy") -> 2023 | G7: 354 | H7: 0.3 | I7: {=_xlfn.IFS(Table1[[#This Row],[Discount]]<=0.2,"Low",Table1[[#This Row],[Discount]]<=0.4,"Medium",Table1[[#This Row],[Discount]]>0.4,"High")} -> Medium | J7: =Table1[[#This Row],[Original Price]]*(1-Table1[[#This Row],[Discount]]) -> 247.8 | K7: =VLOOKUP(B7,customers!$A$2:$D$101,2,0) -> 16 | L7: {=_xlfn.IFS(Table1[[#This Row],[Age]]<=12,"Kids",Table1[[#This Row],[Age]]<=19,"Teenage",Table1[[#This Row],[Age]]<=29,"Young Adult",Table1[[#This Row],[Age]]<=45,"Adult",Table1[[#This Row],[Age]]>=46,"Senior")} -> Teenage | M7: =VLOOKUP(B7,customers!A$2:D$101,3,0) -> Pune | N7: =VLOOKUP(B7,customers!$A$2:$D$101,4,0) -> Maharashtra | O7: =VLOOKUP(C7,'products '!$A$2:$H$3072,2,0) -> Women | P7: =VLOOKUP(C7,'products '!$A$2:$H$3072,3,0) -> Topwear | Q7: =VLOOKUP(C7,'products '!$A$2:$H$3072,4,0) -> T-Shirts | R7: =VLOOKUP(C7,'products '!$A$2:$H$3072,5,0) -> Roadster | S7: =VLOOKUP(C7,'products '!$A$2:$H$3072,6,0) -> 40 | T7: =VLOOKUP(C7,'products '!$A$2:$H$3072,7,0) -> Blue | U7: =VLOOKUP(C7,'products '!$A$2:$H$3072,8,0) -> 5
A8: OD0007 | B8: C007 | C8: P0003 | D8: =RANDBETWEEN(DATE(2021,1,1),DATE(2023,3,31)) -> 44219 | E8: =TEXT(Table1[[#This Row],[Date]],"mmm") -> Jan | F8: =TEXT(Table1[[#This Row],[Date]],"yyyy") -> 2021 | G8: 355 | H8: 0.3 | I8: {=_xlfn.IFS(Table1[[#This Row],[Discount]]<=0.2,"Low",Table1[[#This Row],[Discount]]<=0.4,"Medium",Table1[[#This Row],[Discount]]>0.4,"High")} -> Medium | J8: =Table1[[#This Row],[Original Price]]*(1-Table1[[#This Row],[Discount]]) -> 248.5 | K8: =VLOOKUP(B8,customers!$A$2:$D$101,2,0) -> 23 | L8: {=_xlfn.IFS(Table1[[#This Row],[Age]]<=12,"Kids",Table1[[#This Row],[Age]]<=19,"Teenage",Table1[[#This Row],[Age]]<=29,"Young Adult",Table1[[#This Row],[Age]]<=45,"Adult",Table1[[#This Row],[Age]]>=46,"Senior")} -> Young Adult | M8: =VLOOKUP(B8,customers!A$2:D$101,3,0) -> Pune | N8: =VLOOKUP(B8,customers!$A$2:$D$101,4,0) -> Maharashtra | O8: =VLOOKUP(C8,'products '!$A$2:$H$3072,2,0) -> Women | P8: =VLOOKUP(C8,'products '!$A$2:$H$3072,3,0) -> Topwear | Q8: =VLOOKUP(C8,'products '!$A$2:$H$3072,4,0) -> T-Shirts | R8: =VLOOKUP(C8,'products '!$A$2:$H$3072,5,0) -> Roadster | S8: =VLOOKUP(C8,'products '!$A$2:$H$3072,6,0) -> 42 | T8: =VLOOKUP(C8,'products '!$A$2:$H$3072,7,0) -> White | U8: =VLOOKUP(C8,'products '!$A$2:$H$3072,8,0) -> 3
A9: OD0008 | B9: C008 | C9: P0004 | D9: =RANDBETWEEN(DATE(2021,1,1),DATE(2023,3,31)) -> 44253 | E9: =TEXT(Table1[[#This Row],[Date]],"mmm") -> Feb | F9: =TEXT(Table1[[#This Row],[Date]],"yyyy") -> 2021 | G9: 356 | H9: 0.3 | I9: {=_xlfn.IFS(Table1[[#This Row],[Discount]]<=0.2,"Low",Table1[[#This Row],[Discount]]<=0.4,"Medium",Table1[[#This Row],[Discount]]>0.4,"High")} -> Medium | J9: =Table1[[#This Row],[Original Price]]*(1-Table1[[#This Row],[Discount]]) -> 249.2 | K9: =VLOOKUP(B9,customers!$A$2:$D$101,2,0) -> 22 | L9: {=_xlfn.IFS(Table1[[#This Row],[Age]]<=12,"Kids",Table1[[#This Row],[Age]]<=19,"Teenage",Table1[[#This Row],[Age]]<=29,"Young Adult",Table1[[#This Row],[Age]]<=45,"Adult",Table1[[#This Row],[Age]]>=46,"Senior")} -> Young Adult | M9: =VLOOKUP(B9,customers!A$2:D$101,3,0) -> Pune | N9: =VLOOKUP(B9,customers!$A$2:$D$101,4,0) -> Maharashtra | O9: =VLOOKUP(C9,'products '!$A$2:$H$3072,2,0) -> Women | P9: =VLOOKUP(C9,'products '!$A$2:$H$3072,3,0) -> Topwear | Q9: =VLOOKUP(C9,'products '!$A$2:$H$3072,4,0) -> T-Shirts | R9: =VLOOKUP(C9,'products '!$A$2:$H$3072,5,0) -> Roadster | S9: =VLOOKUP(C9,'products '!$A$2:$H$3072,6,0) -> 44 | T9: =VLOOKUP(C9,'products '!$A$2:$H$3072,7,0) -> Green | U9: =VLOOKUP(C9,'products '!$A$2:$H$3072,8,0) -> 2
A10: OD0009 | B10: C009 | C10: P0005 | D10: =RANDBETWEEN(DATE(2021,1,1),DATE(2023,3,31)) -> 44529 | E10: =TEXT(Table1[[#This Row],[Date]],"mmm") -> Nov | F10: =TEXT(Table1[[#This Row],[Date]],"yyyy") -> 2021 | G10: 2222 | H10: 0.4 | I10: {=_xlfn.IFS(Table1[[#This Row],[Discount]]<=0.2,"Low",Table1[[#This Row],[Discount]]<=0.4,"Medium",Table1[[#This Row],[Discount]]>0.4,"High")} -> Medium | J10: =Table1[[#This Row],[Original Price]]*(1-Table1[[#This Row],[Discount]]) -> 1333.2 | K10: =VLOOKUP(B10,customers!$A$2:$D$101,2,0) -> 17 | L10: {=_xlfn.IFS(Table1[[#This Row],[Age]]<=12,"Kids",Table1[[#This Row],[Age]]<=19,"Teenage",Table1[[#This Row],[Age]]<=29,"Young Adult",Table1[[#This Row],[Age]]<=45,"Adult",Table1[[#This Row],[Age]]>=46,"Senior")} -> Teenage | M10: =VLOOKUP(B10,customers!A$2:D$101,3,0) -> Hyderabad | N10: =VLOOKUP(B10,customers!$A$2:$D$101,4,0) -> Telangana | O10: =VLOOKUP(C10,'products '!$A$2:$H$3072,2,0) -> Women | P10: =VLOOKUP(C10,'products '!$A$2:$H$3072,3,0) -> Topwear | Q10: =VLOOKUP(C10,'products '!$A$2:$H$3072,4,0) -> T-Shirts | R10: =VLOOKUP(C10,'products '!$A$2:$H$3072,5,0) -> Puma | S10: =VLOOKUP(C10,'products '!$A$2:$H$3072,6,0) -> 38 | T10: =VLOOKUP(C10,'products '!$A$2:$H$3072,7,0) -> Olive | U10: =VLOOKUP(C10,'products '!$A$2:$H$3072,8,0) -> 5
A11: OD0010 | B11: C010 | C11: P0006 | D11: =RANDBETWEEN(DATE(2021,1,1),DATE(2023,3,31)) -> 44778 | E11: =TEXT(Table1[[#This Row],[Date]],"mmm") -> Aug | F11: =TEXT(Table1[[#This Row],[Date]],"yyyy") -> 2022 | G11: 2342 | H11: 0.4 | I11: {=_xlfn.IFS(Table1[[#This Row],[Discount]]<=0.2,"Low",Table1[[#This Row],[Discount]]<=0.4,"Medium",Table1[[#This Row],[Discount]]>0.4,"High")} -> Medium | J11: =Table1[[#This Row],[Original Price]]*(1-Table1[[#This Row],[Discount]]) -> 1405.2 | K11: =VLOOKUP(B11,customers!$A$2:$D$101,2,0) -> 19 | L11: {=_xlfn.IFS(Table1[[#This Row],[Age]]<=12,"Kids",Table1[[#This Row],[Age]]<=19,"Teenage",Table1[[#This Row],[Age]]<=29,"Young Adult",Table1[[#This Row],[Age]]<=45,"Adult",Table1[[#This Row],[Age]]>=46,"Senior")} -> Teenage | M11: =VLOOKUP(B11,customers!A$2:D$101,3,0) -> Hyderabad | N11: =VLOOKUP(B11,customers!$A$2:$D$101,4,0) -> Telangana | O11: =VLOOKUP(C11,'products '!$A$2:$H$3072,2,0) -> Women | P11: =VLOOKUP(C11,'products '!$A$2:$H$3072,3,0) -> Topwear | Q11: =VLOOKUP(C11,'products '!$A$2:$H$3072,4,0) -> T-Shirts | R11: =VLOOKUP(C11,'products '!$A$2:$H$3072,5,0) -> Puma | S11: =VLOOKUP(C11,'products '!$A$2:$H$3072,6,0) -> 46 | T11: =VLOOKUP(C11,'products '!$A$2:$H$3072,7,0) -> Pink | U11: =VLOOKUP(C11,'products '!$A$2:$H$3072,8,0) -> 4
A12: OD0011 | B12: C011 | C12: P0007 | D12: =RANDBETWEEN(DATE(2021,1,1),DATE(2023,3,31)) -> 44290 | E12: =TEXT(Table1[[#This Row],[Date]],"mmm") -> Apr | F12: =TEXT(Table1[[#This Row],[Date]],"yyyy") -> 2021 | G12: 2241 | H12: 0.4 | I12: {=_xlfn.IFS(Table1[[#This Row],[Discount]]<=0.2,"Low",Table1[[#This Row],[Discount]]<=0.4,"Medium",Table1[[#This Row],[Discount]]>0.4,"High")} -> Medium | J12: =Table1[[#This Row],[Original Price]]*(1-Table1[[#This Row],[Discount]]) -> 1344.6 | K12: =VLOOKUP(B12,customers!$A$2:$D$101,2,0) -> 18 | L12: {=_xlfn.IFS(Table1[[#This Row],[Age]]<=12,"Kids",Table1[[#This Row],[Age]]<=19,"Teenage",Table1[[#This Row],[Age]]<=29,"Young Adult",Table1[[#This Row],[Age]]<=45,"Adult",Table1[[#This Row],[Age]]>=46,"Senior")} -> Teenage | M12: =VLOOKUP(B12,customers!A$2:D$101,3,0) -> Hyderabad | N12: =VLOOKUP(B12,customers!$A$2:$D$101,4,0) -> Telangana | O12: =VLOOKUP(C12,'products '!$A$2:$H$3072,2,0) -> Women | P12: =VLOOKUP(C12,'products '!$A$2:$H$3072,3,0) -> Topwear | Q12: =VLOOKUP(C12,'products '!$A$2:$H$3072,4,0) -> T-Shirts | R12: =VLOOKUP(C12,'products '!$A$2:$H$3072,5,0) -> Puma | S12: =VLOOKUP(C12,'products '!$A$2:$H$3072,6,0) -> 38 | T12: =VLOOKUP(C12,'products '!$A$2:$H$3072,7,0) -> Orange | U12: =VLOOKUP(C12,'products '!$A$2:$H$3072,8,0) -> 3
A13: OD0012 | B13: C012 | C13: P0007 | D13: =RANDBETWEEN(DATE(2021,1,1),DATE(2023,3,31)) -> 44992 | E13: =TEXT(Table1[[#This Row],[Date]],"mmm") -> Mar | F13: =TEXT(Table1[[#This Row],[Date]],"yyyy") -> 2023 | G13: 2253 | H13: 0.4 | I13: {=_xlfn.IFS(Table1[[#This Row],[Discount]]<=0.2,"Low",Table1[[#This Row],[Discount]]<=0.4,"Medium",Table1[[#This Row],[Discount]]>0.4,"High")} -> Medium | J13: =Table1[[#This Row],[Original Price]]*(1-Table1[[#This Row],[Discount]]) -> 1351.8 | K13: =VLOOKUP(B13,customers!$A$2:$D$101,2,0) -> 20 | L13: {=_xlfn.IFS(Table1[[#This Row],[Age]]<=12,"Kids",Table1[[#This Row],[Age]]<=19,"Teenage",Table1[[#This Row],[Age]]<=29,"Young Adult",Table1[[#This Row],[Age]]<=45,"Adult",Table1[[#This Row],[Age]]>=46,"Senior")} -> Young Adult | M13: =VLOOKUP(B13,customers!A$2:D$101,3,0) -> Hyderabad | N13: =VLOOKUP(B13,customers!$A$2:$D$101,4,0) -> Telangana | O13: =VLOOKUP(C13,'products '!$A$2:$H$3072,2,0) -> Women | P13: =VLOOKUP(C13,'products '!$A$2:$H$3072,3,0) -> Topwear | Q13: =VLOOKUP(C13,'products '!$A$2:$H$3072,4,0) -> T-Shirts | R13: =VLOOKUP(C13,'products '!$A$2:$H$3072,5,0) -> Puma | S13: =VLOOKUP(C13,'products '!$A$2:$H$3072,6,0) -> 38 | T13: =VLOOKUP(C13,'products '!$A$2:$H$3072,7,0) -> Orange | U13: =VLOOKUP(C13,'products '!$A$2:$H$3072,8,0) -> 3
... A3072: OD3071 | B3072: C056 | C3072: P2711 | D3072: =RANDBETWEEN(DATE(2021,1,1),DATE(2023,3,31)) -> 44209 | E3072: =TEXT(Table1[[#This Row],[Date]],"mmm") -> Jan | F3072: =TEXT(Table1[[#This Row],[Date]],"yyyy") -> 2021 | G3072: 555 | H3072: 0.25 | I3072: {=_xlfn.IFS(Table1[[#This Row],[Discount]]<=0.2,"Low",Table1[[#This Row],[Discount]]<=0.4,"Medium",Table1[[#This Row],[Discount]]>0.4,"High")} -> Medium | J3072: =Table1[[#This Row],[Original Price]]*(1-Table1[[#This Row],[Discount]]) -> 416.25 | K3072: =VLOOKUP(B3072,customers!$A$2:$D$101,2,0) -> 19 | L3072: {=_xlfn.IFS(Table1[[#This Row],[Age]]<=12,"Kids",Table1[[#This Row],[Age]]<=19,"Teenage",Table1[[#This Row],[Age]]<=29,"Young Adult",Table1[[#This Row],[Age]]<=45,"Adult",Table1[[#This Row],[Age]]>=46,"Senior")} -> Teenage | M3072: =VLOOKUP(B3072,customers!A$2:D$101,3,0) -> Sagar | N3072: =VLOOKUP(B3072,customers!$A$2:$D$101,4,0) -> Madhya Pradesh | O3072: =VLOOKUP(C3072,'products '!$A$2:$H$3072,2,0) -> Kids | P3072: =VLOOKUP(C3072,'products '!$A$2:$H$3072,3,0) -> Girls Clothing | Q3072: =VLOOKUP(C3072,'products '!$A$2:$H$3072,4,0) -> Shorts | R3072: =VLOOKUP(C3072,'products '!$A$2:$H$3072,5,0) -> Here&Now | S3072: =VLOOKUP(C3072,'products '!$A$2:$H$3072,6,0) -> 5-6Y | T3072: =VLOOKUP(C3072,'products '!$A$2:$H$3072,7,0) -> Sea Green | U3072: =VLOOKUP(C3072,'products '!$A$2:$H$3072,8,0) -> 4
A3073: OD3072 | B3073: C057 | C3073: P2712 | D3073: =RANDBETWEEN(DATE(2021,1,1),DATE(2023,3,31)) -> 44587 | E3073: =TEXT(Table1[[#This Row],[Date]],"mmm") -> Jan | F3073: =TEXT(Table1[[#This Row],[Date]],"yyyy") -> 2022 | G3073: =RANDBETWEEN(600, 2000) -> 1544 | H3073: 0.3 | I3073: {=_xlfn.IFS(Table1[[#This Row],[Discount]]<=0.2,"Low",Table1[[#This Row],[Discount]]<=0.4,"Medium",Table1[[#This Row],[Discount]]>0.4,"High")} -> Medium | J3073: =Table1[[#This Row],[Original Price]]*(1-Table1[[#This Row],[Discount]]) -> 1080.8 | K3073: =VLOOKUP(B3073,customers!$A$2:$D$101,2,0) -> 20 | L3073: {=_xlfn.IFS(Table1[[#This Row],[Age]]<=12,"Kids",Table1[[#This Row],[Age]]<=19,"Teenage",Table1[[#This Row],[Age]]<=29,"Young Adult",Table1[[#This Row],[Age]]<=45,"Adult",Table1[[#This Row],[Age]]>=46,"Senior")} -> Young Adult | M3073: =VLOOKUP(B3073,customers!A$2:D$101,3,0) -> Sagar | N3073: =VLOOKUP(B3073,customers!$A$2:$D$101,4,0) -> Madhya Pradesh | O3073: =VLOOKUP(C3073,'products '!$A$2:$H$3072,2,0) -> Kids | P3073: =VLOOKUP(C3073,'products '!$A$2:$H$3072,3,0) -> Girls Clothing | Q3073: =VLOOKUP(C3073,'products '!$A$2:$H$3072,4,0) -> Shorts | R3073: =VLOOKUP(C3073,'products '!$A$2:$H$3072,5,0) -> Here&Now | S3073: =VLOOKUP(C3073,'products '!$A$2:$H$3072,6,0) -> 5-6Y | T3073: =VLOOKUP(C3073,'products '!$A$2:$H$3072,7,0) -> Yellow | U3073: =VLOOKUP(C3073,'products '!$A$2:$H$3072,8,0) -> 4
A3074: OD3073 | B3074: C058 | C3074: P2713 | D3074: =RANDBETWEEN(DATE(2021,1,1),DATE(2023,3,31)) -> 44711 | E3074: =TEXT(Table1[[#This Row],[Date]],"mmm") -> May | F3074: =TEXT(Table1[[#This Row],[Date]],"yyyy") -> 2022 | G3074: =RANDBETWEEN(600, 2000) -> 753 | H3074: 0.3 | I3074: {=_xlfn.IFS(Table1[[#This Row],[Discount]]<=0.2,"Low",Table1[[#This Row],[Discount]]<=0.4,"Medium",Table1[[#This Row],[Discount]]>0.4,"High")} -> Medium | J3074: =Table1[[#This Row],[Original Price]]*(1-Table1[[#This Row],[Discount]]) -> 527.1 | K3074: =VLOOKUP(B3074,customers!$A$2:$D$101,2,0) -> 21 | L3074: {=_xlfn.IFS(Table1[[#This Row],[Age]]<=12,"Kids",Table1[[#This Row],[Age]]<=19,"Teenage",Table1[[#This Row],[Age]]<=29,"Young Adult",Table1[[#This Row],[Age]]<=45,"Adult",Table1[[#This Row],[Age]]>=46,"Senior")} -> Young Adult | M3074: =VLOOKUP(B3074,customers!A$2:D$101,3,0) -> Indore | N3074: =VLOOKUP(B3074,customers!$A$2:$D$101,4,0) -> Madhya Pradesh | O3074: =VLOOKUP(C3074,'products '!$A$2:$H$3072,2,0) -> Kids | P3074: =VLOOKUP(C3074,'products '!$A$2:$H$3072,3,0) -> Girls Clothing | Q3074: =VLOOKUP(C3074,'products '!$A$2:$H$3072,4,0) -> Shorts | R3074: =VLOOKUP(C3074,'products '!$A$2:$H$3072,5,0) -> Here&Now | S3074: =VLOOKUP(C3074,'products '!$A$2:$H$3072,6,0) -> 5-6Y | T3074: =VLOOKUP(C3074,'products '!$A$2:$H$3072,7,0) -> Blue | U3074: =VLOOKUP(C3074,'products '!$A$2:$H$3072,8,0) -> 3
A3075: OD3074 | B3075: C059 | C3075: P2714 | D3075: =RANDBETWEEN(DATE(2021,1,1),DATE(2023,3,31)) -> 44319 | E3075: =TEXT(Table1[[#This Row],[Date]],"mmm") -> May | F3075: =TEXT(Table1[[#This Row],[Date]],"yyyy") -> 2021 | G3075: =RANDBETWEEN(600, 2000) -> 1354 | H3075: 0.3 | I3075: {=_xlfn.IFS(Table1[[#This Row],[Discount]]<=0.2,"Low",Table1[[#This Row],[Discount]]<=0.4,"Medium",Table1[[#This Row],[Discount]]>0.4,"High")} -> Medium | J3075: =Table1[[#This Row],[Original Price]]*(1-Table1[[#This Row],[Discount]]) -> 947.8 | K3075: =VLOOKUP(B3075,customers!$A$2:$D$101,2,0) -> 22 | L3075: {=_xlfn.IFS(Table1[[#This Row],[Age]]<=12,"Kids",Table1[[#This Row],[Age]]<=19,"Teenage",Table1[[#This Row],[Age]]<=29,"Young Adult",Table1[[#This Row],[Age]]<=45,"Adult",Table1[[#This Row],[Age]]>=46,"Senior")} -> Young Adult | M3075: =VLOOKUP(B3075,customers!A$2:D$101,3,0) -> Indore | N3075: =VLOOKUP(B3075,customers!$A$2:$D$101,4,0) -> Madhya Pradesh | O3075: =VLOOKUP(C3075,'products '!$A$2:$H$3072,2,0) -> Kids | P3075: =VLOOKUP(C3075,'products '!$A$2:$H$3072,3,0) -> Girls Clothing | Q3075: =VLOOKUP(C3075,'products '!$A$2:$H$3072,4,0) -> Shorts | R3075: =VLOOKUP(C3075,'products '!$A$2:$H$3072,5,0) -> Here&Now | S3075: =VLOOKUP(C3075,'products '!$A$2:$H$3072,6,0) -> 5-6Y | T3075: =VLOOKUP(C3075,'products '!$A$2:$H$3072,7,0) -> White | U3075: =VLOOKUP(C3075,'products '!$A$2:$H$3072,8,0) -> 5
A3076: OD3075 | B3076: C060 | C3076: P2715 | D3076: =RANDBETWEEN(DATE(2021,1,1),DATE(2023,3,31)) -> 44565 | E3076: =TEXT(Table1[[#This Row],[Date]],"mmm") -> Jan | F3076: =TEXT(Table1[[#This Row],[Date]],"yyyy") -> 2022 | G3076: =RANDBETWEEN(600, 2000) -> 1989 | H3076: 0.25 | I3076: {=_xlfn.IFS(Table1[[#This Row],[Discount]]<=0.2,"Low",Table1[[#This Row],[Discount]]<=0.4,"Medium",Table1[[#This Row],[Discount]]>0.4,"High")} -> Medium | J3076: =Table1[[#This Row],[Original Price]]*(1-Table1[[#This Row],[Discount]]) -> 1491.75 | K3076: =VLOOKUP(B3076,customers!$A$2:$D$101,2,0) -> 16 | L3076: {=_xlfn.IFS(Table1[[#This Row],[Age]]<=12,"Kids",Table1[[#This Row],[Age]]<=19,"Teenage",Table1[[#This Row],[Age]]<=29,"Young Adult",Table1[[#This Row],[Age]]<=45,"Adult",Table1[[#This Row],[Age]]>=46,"Senior")} -> Teenage | M3076: =VLOOKUP(B3076,customers!A$2:D$101,3,0) -> Kanpur | N3076: =VLOOKUP(B3076,customers!$A$2:$D$101,4,0) -> Uttar Pradesh | O3076: =VLOOKUP(C3076,'products '!$A$2:$H$3072,2,0) -> Kids | P3076: =VLOOKUP(C3076,'products '!$A$2:$H$3072,3,0) -> Girls Clothing | Q3076: =VLOOKUP(C3076,'products '!$A$2:$H$3072,4,0) -> Shorts | R3076: =VLOOKUP(C3076,'products '!$A$2:$H$3072,5,0) -> Here&Now | S3076: =VLOOKUP(C3076,'products '!$A$2:$H$3072,6,0) -> 5-6Y | T3076: =VLOOKUP(C3076,'products '!$A$2:$H$3072,7,0) -> Green | U3076: =VLOOKUP(C3076,'products '!$A$2:$H$3072,8,0) -> 4
A3077: OD3076 | B3077: C061 | C3077: P2716 | D3077: =RANDBETWEEN(DATE(2021,1,1),DATE(2023,3,31)) -> 44785 | E3077: =TEXT(Table1[[#This Row],[Date]],"mmm") -> Aug | F3077: =TEXT(Table1[[#This Row],[Date]],"yyyy") -> 2022 | G3077: =RANDBETWEEN(600, 2000) -> 791 | H3077: 0.25 | I3077: {=_xlfn.IFS(Table1[[#This Row],[Discount]]<=0.2,"Low",Table1[[#This Row],[Discount]]<=0.4,"Medium",Table1[[#This Row],[Discount]]>0.4,"High")} -> Medium | J3077: =Table1[[#This Row],[Original Price]]*(1-Table1[[#This Row],[Discount]]) -> 593.25 | K3077: =VLOOKUP(B3077,customers!$A$2:$D$101,2,0) -> 17 | L3077: {=_xlfn.IFS(Table1[[#This Row],[Age]]<=12,"Kids",Table1[[#This Row],[Age]]<=19,"Teenage",Table1[[#This Row],[Age]]<=29,"Young Adult",Table1[[#This Row],[Age]]<=45,"Adult",Table1[[#This Row],[Age]]>=46,"Senior")} -> Teenage | M3077: =VLOOKUP(B3077,customers!A$2:D$101,3,0) -> Kanpur | N3077: =VLOOKUP(B3077,customers!$A$2:$D$101,4,0) -> Uttar Pradesh | O3077: =VLOOKUP(C3077,'products '!$A$2:$H$3072,2,0) -> Kids | P3077: =VLOOKUP(C3077,'products '!$A$2:$H$3072,3,0) -> Girls Clothing | Q3077: =VLOOKUP(C3077,'products '!$A$2:$H$3072,4,0) -> Shorts | R3077: =VLOOKUP(C3077,'products '!$A$2:$H$3072,5,0) -> Here&Now | S3077: =VLOOKUP(C3077,'products '!$A$2:$H$3072,6,0) -> 5-6Y | T3077: =VLOOKUP(C3077,'products '!$A$2:$H$3072,7,0) -> Olive | U3077: =VLOOKUP(C3077,'products '!$A$2:$H$3072,8,0) -> 2
A3078: OD3077 | B3078: C062 | C3078: P2717 | D3078: =RANDBETWEEN(DATE(2021,1,1),DATE(2023,3,31)) -> 44534 | E3078: =TEXT(Table1[[#This Row],[Date]],"mmm") -> Dec | F3078: =TEXT(Table1[[#This Row],[Date]],"yyyy") -> 2021 | G3078: =RANDBETWEEN(600, 2000) -> 1415 | H3078: 0.3 | I3078: {=_xlfn.IFS(Table1[[#This Row],[Discount]]<=0.2,"Low",Table1[[#This Row],[Discount]]<=0.4,"Medium",Table1[[#This Row],[Discount]]>0.4,"High")} -> Medium | J3078: =Table1[[#This Row],[Original Price]]*(1-Table1[[#This Row],[Discount]]) -> 990.5 | K3078: =VLOOKUP(B3078,customers!$A$2:$D$101,2,0) -> 18 | L3078: {=_xlfn.IFS(Table1[[#This Row],[Age]]<=12,"Kids",Table1[[#This Row],[Age]]<=19,"Teenage",Table1[[#This Row],[Age]]<=29,"Young Adult",Table1[[#This Row],[Age]]<=45,"Adult",Table1[[#This Row],[Age]]>=46,"Senior")} -> Teenage | M3078: =VLOOKUP(B3078,customers!A$2:D$101,3,0) -> Kanpur | N3078: =VLOOKUP(B3078,customers!$A$2:$D$101,4,0) -> Uttar Pradesh | O3078: =VLOOKUP(C3078,'products '!$A$2:$H$3072,2,0) -> Kids | P3078: =VLOOKUP(C3078,'products '!$A$2:$H$3072,3,0) -> Girls Clothing | Q3078: =VLOOKUP(C3078,'products '!$A$2:$H$3072,4,0) -> Shorts | R3078: =VLOOKUP(C3078,'products '!$A$2:$H$3072,5,0) -> HRX by Hrithik Roshan | S3078: =VLOOKUP(C3078,'products '!$A$2:$H$3072,6,0) -> 5-6Y | T3078: =VLOOKUP(C3078,'products '!$A$2:$H$3072,7,0) -> Pink | U3078: =VLOOKUP(C3078,'products '!$A$2:$H$3072,8,0) -> 5
A3079: OD3078 | B3079: C063 | C3079: P2718 | D3079: =RANDBETWEEN(DATE(2021,1,1),DATE(2023,3,31)) -> 44371 | E3079: =TEXT(Table1[[#This Row],[Date]],"mmm") -> Jun | F3079: =TEXT(Table1[[#This Row],[Date]],"yyyy") -> 2021 | G3079: =RANDBETWEEN(600, 2000) -> 953 | H3079: 0.3 | I3079: {=_xlfn.IFS(Table1[[#This Row],[Discount]]<=0.2,"Low",Table1[[#This Row],[Discount]]<=0.4,"Medium",Table1[[#This Row],[Discount]]>0.4,"High")} -> Medium | J3079: =Table1[[#This Row],[Original Price]]*(1-Table1[[#This Row],[Discount]]) -> 667.1 | K3079: =VLOOKUP(B3079,customers!$A$2:$D$101,2,0) -> 19 | L3079: {=_xlfn.IFS(Table1[[#This Row],[Age]]<=12,"Kids",Table1[[#This Row],[Age]]<=19,"Teenage",Table1[[#This Row],[Age]]<=29,"Young Adult",Table1[[#This Row],[Age]]<=45,"Adult",Table1[[#This Row],[Age]]>=46,"Senior")} -> Teenage | M3079: =VLOOKUP(B3079,customers!A$2:D$101,3,0) -> Kanpur | N3079: =VLOOKUP(B3079,customers!$A$2:$D$101,4,0) -> Uttar Pradesh | O3079: =VLOOKUP(C3079,'products '!$A$2:$H$3072,2,0) -> Kids | P3079: =VLOOKUP(C3079,'products '!$A$2:$H$3072,3,0) -> Girls Clothing | Q3079: =VLOOKUP(C3079,'products '!$A$2:$H$3072,4,0) -> Shorts | R3079: =VLOOKUP(C3079,'products '!$A$2:$H$3072,5,0) -> HRX by Hrithik Roshan | S3079: =VLOOKUP(C3079,'products '!$A$2:$H$3072,6,0) -> 5-6Y | T3079: =VLOOKUP(C3079,'products '!$A$2:$H$3072,7,0) -> Orange | U3079: =VLOOKUP(C3079,'products '!$A$2:$H$3072,8,0) -> 5
A3080: OD3079 | B3080: C064 | C3080: P2719 | D3080: =RANDBETWEEN(DATE(2021,1,1),DATE(2023,3,31)) -> 44924 | E3080: =TEXT(Table1[[#This Row],[Date]],"mmm") -> Dec | F3080: =TEXT(Table1[[#This Row],[Date]],"yyyy") -> 2022 | G3080: =RANDBETWEEN(600, 2000) -> 720 | H3080: 0.3 | I3080: {=_xlfn.IFS(Table1[[#This Row],[Discount]]<=0.2,"Low",Table1[[#This Row],[Discount]]<=0.4,"Medium",Table1[[#This Row],[Discount]]>0.4,"High")} -> Medium | J3080: =Table1[[#This Row],[Original Price]]*(1-Table1[[#This Row],[Discount]]) -> 504 | K3080: =VLOOKUP(B3080,customers!$A$2:$D$101,2,0) -> 20 | L3080: {=_xlfn.IFS(Table1[[#This Row],[Age]]<=12,"Kids",Table1[[#This Row],[Age]]<=19,"Teenage",Table1[[#This Row],[Age]]<=29,"Young Adult",Table1[[#This Row],[Age]]<=45,"Adult",Table1[[#This Row],[Age]]>=46,"Senior")} -> Young Adult | M3080: =VLOOKUP(B3080,customers!A$2:D$101,3,0) -> Aligarh | N3080: =VLOOKUP(B3080,customers!$A$2:$D$101,4,0) -> Uttar Pradesh | O3080: =VLOOKUP(C3080,'products '!$A$2:$H$3072,2,0) -> Kids | P3080: =VLOOKUP(C3080,'products '!$A$2:$H$3072,3,0) -> Girls Clothing | Q3080: =VLOOKUP(C3080,'products '!$A$2:$H$3072,4,0) -> Shorts | R3080: =VLOOKUP(C3080,'products '!$A$2:$H$3072,5,0) -> HRX by Hrithik Roshan | S3080: =VLOOKUP(C3080,'products '!$A$2:$H$3072,6,0) -> 5-6Y | T3080: =VLOOKUP(C3080,'products '!$A$2:$H$3072,7,0) -> Yellow | U3080: =VLOOKUP(C3080,'products '!$A$2:$H$3072,8,0) -> 5
A3081: OD3080 | B3081: C065 | C3081: P2720 | D3081: =RANDBETWEEN(DATE(2021,1,1),DATE(2023,3,31)) -> 44754 | E3081: =TEXT(Table1[[#This Row],[Date]],"mmm") -> Jul | F3081: =TEXT(Table1[[#This Row],[Date]],"yyyy") -> 2022 | G3081: =RANDBETWEEN(600, 2000) -> 1230 | H3081: 0.4 | I3081: {=_xlfn.IFS(Table1[[#This Row],[Discount]]<=0.2,"Low",Table1[[#This Row],[Discount]]<=0.4,"Medium",Table1[[#This Row],[Discount]]>0.4,"High")} -> Medium | J3081: =Table1[[#This Row],[Original Price]]*(1-Table1[[#This Row],[Discount]]) -> 738 | K3081: =VLOOKUP(B3081,customers!$A$2:$D$101,2,0) -> 21 | L3081: {=_xlfn.IFS(Table1[[#This Row],[Age]]<=12,"Kids",Table1[[#This Row],[Age]]<=19,"Teenage",Table1[[#This Row],[Age]]<=29,"Young Adult",Table1[[#This Row],[Age]]<=45,"Adult",Table1[[#This Row],[Age]]>=46,"Senior")} -> Young Adult | M3081: =VLOOKUP(B3081,customers!A$2:D$101,3,0) -> Aligarh | N3081: =VLOOKUP(B3081,customers!$A$2:$D$101,4,0) -> Uttar Pradesh | O3081: =VLOOKUP(C3081,'products '!$A$2:$H$3072,2,0) -> Kids | P3081: =VLOOKUP(C3081,'products '!$A$2:$H$3072,3,0) -> Girls Clothing | Q3081: =VLOOKUP(C3081,'products '!$A$2:$H$3072,4,0) -> Shorts | R3081: =VLOOKUP(C3081,'products '!$A$2:$H$3072,5,0) -> HRX by Hrithik Roshan | S3081: =VLOOKUP(C3081,'products '!$A$2:$H$3072,6,0) -> 5-6Y | T3081: =VLOOKUP(C3081,'products '!$A$2:$H$3072,7,0) -> Yellow | U3081: =VLOOKUP(C3081,'products '!$A$2:$H$3072,8,0) -> 4
A3082: OD3081 | B3082: C066 | C3082: P2721 | D3082: =RANDBETWEEN(DATE(2021,1,1),DATE(2023,3,31)) -> 44801 | E3082: =TEXT(Table1[[#This Row],[Date]],"mmm") -> Aug | F3082: =TEXT(Table1[[#This Row],[Date]],"yyyy") -> 2022 | G3082: =RANDBETWEEN(600, 2000) -> 624 | H3082: 0.4 | I3082: {=_xlfn.IFS(Table1[[#This Row],[Discount]]<=0.2,"Low",Table1[[#This Row],[Discount]]<=0.4,"Medium",Table1[[#This Row],[Discount]]>0.4,"High")} -> Medium | J3082: =Table1[[#This Row],[Original Price]]*(1-Table1[[#This Row],[Discount]]) -> 374.4 | K3082: =VLOOKUP(B3082,customers!$A$2:$D$101,2,0) -> 22 | L3082: {=_xlfn.IFS(Table1[[#This Row],[Age]]<=12,"Kids",Table1[[#This Row],[Age]]<=19,"Teenage",Table1[[#This Row],[Age]]<=29,"Young Adult",Table1[[#This Row],[Age]]<=45,"Adult",Table1[[#This Row],[Age]]>=46,"Senior")} -> Young Adult | M3082: =VLOOKUP(B3082,customers!A$2:D$101,3,0) -> Aligarh | N3082: =VLOOKUP(B3082,customers!$A$2:$D$101,4,0) -> Uttar Pradesh | O3082: =VLOOKUP(C3082,'products '!$A$2:$H$3072,2,0) -> Kids | P3082: =VLOOKUP(C3082,'products '!$A$2:$H$3072,3,0) -> Girls Clothing | Q3082: =VLOOKUP(C3082,'products '!$A$2:$H$3072,4,0) -> Shorts | R3082: =VLOOKUP(C3082,'products '!$A$2:$H$3072,5,0) -> HRX by Hrithik Roshan | S3082: =VLOOKUP(C3082,'products '!$A$2:$H$3072,6,0) -> 2-3Y | T3082: =VLOOKUP(C3082,'products '!$A$2:$H$3072,7,0) -> Yellow | U3082: =VLOOKUP(C3082,'products '!$A$2:$H$3072,8,0) -> 4
A3083: OD3082 | B3083: C067 | C3083: P2722 | D3083: =RANDBETWEEN(DATE(2021,1,1),DATE(2023,3,31)) -> 44994 | E3083: =TEXT(Table1[[#This Row],[Date]],"mmm") -> Mar | F3083: =TEXT(Table1[[#This Row],[Date]],"yyyy") -> 2023 | G3083: =RANDBETWEEN(600, 2000) -> 941 | H3083: 0.4 | I3083: {=_xlfn.IFS(Table1[[#This Row],[Discount]]<=0.2,"Low",Table1[[#This Row],[Discount]]<=0.4,"Medium",Table1[[#This Row],[Discount]]>0.4,"High")} -> Medium | J3083: =Table1[[#This Row],[Original Price]]*(1-Table1[[#This Row],[Discount]]) -> 564.6 | K3083: =VLOOKUP(B3083,customers!$A$2:$D$101,2,0) -> 23 | L3083: {=_xlfn.IFS(Table1[[#This Row],[Age]]<=12,"Kids",Table1[[#This Row],[Age]]<=19,"Teenage",Table1[[#This Row],[Age]]<=29,"Young Adult",Table1[[#This Row],[Age]]<=45,"Adult",Table1[[#This Row],[Age]]>=46,"Senior")} -> Young Adult | M3083: =VLOOKUP(B3083,customers!A$2:D$101,3,0) -> Aligarh | N3083: =VLOOKUP(B3083,customers!$A$2:$D$101,4,0) -> Uttar Pradesh | O3083: =VLOOKUP(C3083,'products '!$A$2:$H$3072,2,0) -> Kids | P3083: =VLOOKUP(C3083,'products '!$A$2:$H$3072,3,0) -> Girls Clothing | Q3083: =VLOOKUP(C3083,'products '!$A$2:$H$3072,4,0) -> Shorts | R3083: =VLOOKUP(C3083,'products '!$A$2:$H$3072,5,0) -> HRX by Hrithik Roshan | S3083: =VLOOKUP(C3083,'products '!$A$2:$H$3072,6,0) -> 2-3Y | T3083: =VLOOKUP(C3083,'products '!$A$2:$H$3072,7,0) -> Yellow | U3083: =VLOOKUP(C3083,'products '!$A$2:$H$3072,8,0) -> 4
A3084: OD3083 | B3084: C068 | C3084: P2723 | D3084: =RANDBETWEEN(DATE(2021,1,1),DATE(2023,3,31)) -> 44996 | E3084: =TEXT(Table1[[#This Row],[Date]],"mmm") -> Mar | F3084: =TEXT(Table1[[#This Row],[Date]],"yyyy") -> 2023 | G3084: =RANDBETWEEN(600, 2000) -> 1031 | H3084: 0.4 | I3084: {=_xlfn.IFS(Table1[[#This Row],[Discount]]<=0.2,"Low",Table1[[#This Row],[Discount]]<=0.4,"Medium",Table1[[#This Row],[Discount]]>0.4,"High")} -> Medium | J3084: =Table1[[#This Row],[Original Price]]*(1-Table1[[#This Row],[Discount]]) -> 618.6 | K3084: =VLOOKUP(B3084,customers!$A$2:$D$101,2,0) -> 18 | L3084: {=_xlfn.IFS(Table1[[#This Row],[Age]]<=12,"Kids",Table1[[#This Row],[Age]]<=19,"Teenage",Table1[[#This Row],[Age]]<=29,"Young Adult",Table1[[#This Row],[Age]]<=45,"Adult",Table1[[#This Row],[Age]]>=46,"Senior")} -> Teenage | M3084: =VLOOKUP(B3084,customers!A$2:D$101,3,0) -> Prayagraj | N3084: =VLOOKUP(B3084,customers!$A$2:$D$101,4,0) -> Uttar Pradesh | O3084: =VLOOKUP(C3084,'products '!$A$2:$H$3072,2,0) -> Kids | P3084: =VLOOKUP(C3084,'products '!$A$2:$H$3072,3,0) -> Girls Clothing | Q3084: =VLOOKUP(C3084,'products '!$A$2:$H$3072,4,0) -> Shorts | R3084: =VLOOKUP(C3084,'products '!$A$2:$H$3072,5,0) -> HRX by Hrithik Roshan | S3084: =VLOOKUP(C3084,'products '!$A$2:$H$3072,6,0) -> 2-3Y | T3084: =VLOOKUP(C3084,'products '!$A$2:$H$3072,7,0) -> Yellow | U3084: =VLOOKUP(C3084,'products '!$A$2:$H$3072,8,0) -> 5
... A3447: OD3446 | B3447: C031 | C3447: P3046 | D3447: =RANDBETWEEN(DATE(2021,1,1),DATE(2023,3,31)) -> 44460 | E3447: =TEXT(Table1[[#This Row],[Date]],"mmm") -> Sep | F3447: =TEXT(Table1[[#This Row],[Date]],"yyyy") -> 2021 | G3447: =RANDBETWEEN(600, 2000) -> 1229 | H3447: 0.39 | I3447: {=_xlfn.IFS(Table1[[#This Row],[Discount]]<=0.2,"Low",Table1[[#This Row],[Discount]]<=0.4,"Medium",Table1[[#This Row],[Discount]]>0.4,"High")} -> Medium | J3447: =Table1[[#This Row],[Original Price]]*(1-Table1[[#This Row],[Discount]]) -> 749.69 | K3447: =VLOOKUP(B3447,customers!$A$2:$D$101,2,0) -> 29 | L3447: {=_xlfn.IFS(Table1[[#This Row],[Age]]<=12,"Kids",Table1[[#This Row],[Age]]<=19,"Teenage",Table1[[#This Row],[Age]]<=29,"Young Adult",Table1[[#This Row],[Age]]<=45,"Adult",Table1[[#This Row],[Age]]>=46,"Senior")} -> Young Adult | M3447: =VLOOKUP(B3447,customers!A$2:D$101,3,0) -> Bengaluru | N3447: =VLOOKUP(B3447,customers!$A$2:$D$101,4,0) -> Karnataka | O3447: =VLOOKUP(C3447,'products '!$A$2:$H$3072,2,0) -> Kids | P3447: =VLOOKUP(C3447,'products '!$A$2:$H$3072,3,0) -> Footwear | Q3447: =VLOOKUP(C3447,'products '!$A$2:$H$3072,4,0) -> Sandals | R3447: =VLOOKUP(C3447,'products '!$A$2:$H$3072,5,0) -> MAX | S3447: =VLOOKUP(C3447,'products '!$A$2:$H$3072,6,0) -> 6-9M | T3447: =VLOOKUP(C3447,'products '!$A$2:$H$3072,7,0) -> Maroon | U3447: =VLOOKUP(C3447,'products '!$A$2:$H$3072,8,0) -> 3
A3448: OD3447 | B3448: C032 | C3448: P3047 | D3448: =RANDBETWEEN(DATE(2021,1,1),DATE(2023,3,31)) -> 44542 | E3448: =TEXT(Table1[[#This Row],[Date]],"mmm") -> Dec | F3448: =TEXT(Table1[[#This Row],[Date]],"yyyy") -> 2021 | G3448: 2245 | H3448: 0.39 | I3448: {=_xlfn.IFS(Table1[[#This Row],[Discount]]<=0.2,"Low",Table1[[#This Row],[Discount]]<=0.4,"Medium",Table1[[#This Row],[Discount]]>0.4,"High")} -> Medium | J3448: =Table1[[#This Row],[Original Price]]*(1-Table1[[#This Row],[Discount]]) -> 1369.45 | K3448: =VLOOKUP(B3448,customers!$A$2:$D$101,2,0) -> 41 | L3448: {=_xlfn.IFS(Table1[[#This Row],[Age]]<=12,"Kids",Table1[[#This Row],[Age]]<=19,"Teenage",Table1[[#This Row],[Age]]<=29,"Young Adult",Table1[[#This Row],[Age]]<=45,"Adult",Table1[[#This Row],[Age]]>=46,"Senior")} -> Adult | M3448: =VLOOKUP(B3448,customers!A$2:D$101,3,0) -> Bengaluru | N3448: =VLOOKUP(B3448,customers!$A$2:$D$101,4,0) -> Karnataka | O3448: =VLOOKUP(C3448,'products '!$A$2:$H$3072,2,0) -> Kids | P3448: =VLOOKUP(C3448,'products '!$A$2:$H$3072,3,0) -> Footwear | Q3448: =VLOOKUP(C3448,'products '!$A$2:$H$3072,4,0) -> Sandals | R3448: =VLOOKUP(C3448,'products '!$A$2:$H$3072,5,0) -> Puma | S3448: =VLOOKUP(C3448,'products '!$A$2:$H$3072,6,0) -> 6-9M | T3448: =VLOOKUP(C3448,'products '!$A$2:$H$3072,7,0) -> Maroon | U3448: =VLOOKUP(C3448,'products '!$A$2:$H$3072,8,0) -> 2
A3449: OD3448 | B3449: C033 | C3449: P3048 | D3449: =RANDBETWEEN(DATE(2021,1,1),DATE(2023,3,31)) -> 44377 | E3449: =TEXT(Table1[[#This Row],[Date]],"mmm") -> Jun | F3449: =TEXT(Table1[[#This Row],[Date]],"yyyy") -> 2021 | G3449: 2354 | H3449: 0.39 | I3449: {=_xlfn.IFS(Table1[[#This Row],[Discount]]<=0.2,"Low",Table1[[#This Row],[Discount]]<=0.4,"Medium",Table1[[#This Row],[Discount]]>0.4,"High")} -> Medium | J3449: =Table1[[#This Row],[Original Price]]*(1-Table1[[#This Row],[Discount]]) -> 1435.94 | K3449: =VLOOKUP(B3449,customers!$A$2:$D$101,2,0) -> 42 | L3449: {=_xlfn.IFS(Table1[[#This Row],[Age]]<=12,"Kids",Table1[[#This Row],[Age]]<=19,"Teenage",Table1[[#This Row],[Age]]<=29,"Young Adult",Table1[[#This Row],[Age]]<=45,"Adult",Table1[[#This Row],[Age]]>=46,"Senior")} -> Adult | M3449: =VLOOKUP(B3449,customers!A$2:D$101,3,0) -> Bengaluru | N3449: =VLOOKUP(B3449,customers!$A$2:$D$101,4,0) -> Karnataka | O3449: =VLOOKUP(C3449,'products '!$A$2:$H$3072,2,0) -> Kids | P3449: =VLOOKUP(C3449,'products '!$A$2:$H$3072,3,0) -> Footwear | Q3449: =VLOOKUP(C3449,'products '!$A$2:$H$3072,4,0) -> Sandals | R3449: =VLOOKUP(C3449,'products '!$A$2:$H$3072,5,0) -> Puma | S3449: =VLOOKUP(C3449,'products '!$A$2:$H$3072,6,0) -> 6-9M | T3449: =VLOOKUP(C3449,'products '!$A$2:$H$3072,7,0) -> Maroon | U3449: =VLOOKUP(C3449,'products '!$A$2:$H$3072,8,0) -> 5
A3450: OD3449 | B3450: C034 | C3450: P3049 | D3450: =RANDBETWEEN(DATE(2021,1,1),DATE(2023,3,31)) -> 44330 | E3450: =TEXT(Table1[[#This Row],[Date]],"mmm") -> May | F3450: =TEXT(Table1[[#This Row],[Date]],"yyyy") -> 2021 | G3450: 2214 | H3450: 0.39 | I3450: {=_xlfn.IFS(Table1[[#This Row],[Discount]]<=0.2,"Low",Table1[[#This Row],[Discount]]<=0.4,"Medium",Table1[[#This Row],[Discount]]>0.4,"High")} -> Medium | J3450: =Table1[[#This Row],[Original Price]]*(1-Table1[[#This Row],[Discount]]) -> 1350.54 | K3450: =VLOOKUP(B3450,customers!$A$2:$D$101,2,0) -> 43 | L3450: {=_xlfn.IFS(Table1[[#This Row],[Age]]<=12,"Kids",Table1[[#This Row],[Age]]<=19,"Teenage",Table1[[#This Row],[Age]]<=29,"Young Adult",Table1[[#This Row],[Age]]<=45,"Adult",Table1[[#This Row],[Age]]>=46,"Senior")} -> Adult | M3450: =VLOOKUP(B3450,customers!A$2:D$101,3,0) -> Bengaluru | N3450: =VLOOKUP(B3450,customers!$A$2:$D$101,4,0) -> Karnataka | O3450: =VLOOKUP(C3450,'products '!$A$2:$H$3072,2,0) -> Kids | P3450: =VLOOKUP(C3450,'products '!$A$2:$H$3072,3,0) -> Footwear | Q3450: =VLOOKUP(C3450,'products '!$A$2:$H$3072,4,0) -> Sandals | R3450: =VLOOKUP(C3450,'products '!$A$2:$H$3072,5,0) -> Puma | S3450: =VLOOKUP(C3450,'products '!$A$2:$H$3072,6,0) -> 6-9M | T3450: =VLOOKUP(C3450,'products '!$A$2:$H$3072,7,0) -> Grey | U3450: =VLOOKUP(C3450,'products '!$A$2:$H$3072,8,0) -> 4
A3451: OD3450 | B3451: C035 | C3451: P3050 | D3451: =RANDBETWEEN(DATE(2021,1,1),DATE(2023,3,31)) -> 44675 | E3451: =TEXT(Table1[[#This Row],[Date]],"mmm") -> Apr | F3451: =TEXT(Table1[[#This Row],[Date]],"yyyy") -> 2022 | G3451: 2365 | H3451: 0.3 | I3451: {=_xlfn.IFS(Table1[[#This Row],[Discount]]<=0.2,"Low",Table1[[#This Row],[Discount]]<=0.4,"Medium",Table1[[#This Row],[Discount]]>0.4,"High")} -> Medium | J3451: =Table1[[#This Row],[Original Price]]*(1-Table1[[#This Row],[Discount]]) -> 1655.5 | K3451: =VLOOKUP(B3451,customers!$A$2:$D$101,2,0) -> 44 | L3451: {=_xlfn.IFS(Table1[[#This Row],[Age]]<=12,"Kids",Table1[[#This Row],[Age]]<=19,"Teenage",Table1[[#This Row],[Age]]<=29,"Young Adult",Table1[[#This Row],[Age]]<=45,"Adult",Table1[[#This Row],[Age]]>=46,"Senior")} -> Adult | M3451: =VLOOKUP(B3451,customers!A$2:D$101,3,0) -> Bengaluru | N3451: =VLOOKUP(B3451,customers!$A$2:$D$101,4,0) -> Karnataka | O3451: =VLOOKUP(C3451,'products '!$A$2:$H$3072,2,0) -> Kids | P3451: =VLOOKUP(C3451,'products '!$A$2:$H$3072,3,0) -> Footwear | Q3451: =VLOOKUP(C3451,'products '!$A$2:$H$3072,4,0) -> Sandals | R3451: =VLOOKUP(C3451,'products '!$A$2:$H$3072,5,0) -> Puma | S3451: =VLOOKUP(C3451,'products '!$A$2:$H$3072,6,0) -> 6-9M | T3451: =VLOOKUP(C3451,'products '!$A$2:$H$3072,7,0) -> Grey | U3451: =VLOOKUP(C3451,'products '!$A$2:$H$3072,8,0) -> 2
A3452: OD3451 | B3452: C036 | C3452: P3051 | D3452: =RANDBETWEEN(DATE(2021,1,1),DATE(2023,3,31)) -> 44298 | E3452: =TEXT(Table1[[#This Row],[Date]],"mmm") -> Apr | F3452: =TEXT(Table1[[#This Row],[Date]],"yyyy") -> 2021 | G3452: 2541 | H3452: 0.3 | I3452: {=_xlfn.IFS(Table1[[#This Row],[Discount]]<=0.2,"Low",Table1[[#This Row],[Discount]]<=0.4,"Medium",Table1[[#This Row],[Discount]]>0.4,"High")} -> Medium | J3452: =Table1[[#This Row],[Original Price]]*(1-Table1[[#This Row],[Discount]]) -> 1778.7 | K3452: =VLOOKUP(B3452,customers!$A$2:$D$101,2,0) -> 45 | L3452: {=_xlfn.IFS(Table1[[#This Row],[Age]]<=12,"Kids",Table1[[#This Row],[Age]]<=19,"Teenage",Table1[[#This Row],[Age]]<=29,"Young Adult",Table1[[#This Row],[Age]]<=45,"Adult",Table1[[#This Row],[Age]]>=46,"Senior")} -> Adult | M3452: =VLOOKUP(B3452,customers!A$2:D$101,3,0) -> Bengaluru | N3452: =VLOOKUP(B3452,customers!$A$2:$D$101,4,0) -> Karnataka | O3452: =VLOOKUP(C3452,'products '!$A$2:$H$3072,2,0) -> Kids | P3452: =VLOOKUP(C3452,'products '!$A$2:$H$3072,3,0) -> Footwear | Q3452: =VLOOKUP(C3452,'products '!$A$2:$H$3072,4,0) -> Sandals | R3452: =VLOOKUP(C3452,'products '!$A$2:$H$3072,5,0) -> Puma | S3452: =VLOOKUP(C3452,'products '!$A$2:$H$3072,6,0) -> 6-9M | T3452: =VLOOKUP(C3452,'products '!$A$2:$H$3072,7,0) -> Grey | U3452: =VLOOKUP(C3452,'products '!$A$2:$H$3072,8,0) -> 5
A3453: OD3452 | B3453: C037 | C3453: P3052 | D3453: =RANDBETWEEN(DATE(2021,1,1),DATE(2023,3,31)) -> 44533 | E3453: =TEXT(Table1[[#This Row],[Date]],"mmm") -> Dec | F3453: =TEXT(Table1[[#This Row],[Date]],"yyyy") -> 2021 | G3453: 1235 | H3453: 0.3 | I3453: {=_xlfn.IFS(Table1[[#This Row],[Discount]]<=0.2,"Low",Table1[[#This Row],[Discount]]<=0.4,"Medium",Table1[[#This Row],[Discount]]>0.4,"High")} -> Medium | J3453: =Table1[[#This Row],[Original Price]]*(1-Table1[[#This Row],[Discount]]) -> 864.5 | K3453: =VLOOKUP(B3453,customers!$A$2:$D$101,2,0) -> 35 | L3453: {=_xlfn.IFS(Table1[[#This Row],[Age]]<=12,"Kids",Table1[[#This Row],[Age]]<=19,"Teenage",Table1[[#This Row],[Age]]<=29,"Young Adult",Table1[[#This Row],[Age]]<=45,"Adult",Table1[[#This Row],[Age]]>=46,"Senior")} -> Adult | M3453: =VLOOKUP(B3453,customers!A$2:D$101,3,0) -> Bengaluru | N3453: =VLOOKUP(B3453,customers!$A$2:$D$101,4,0) -> Karnataka | O3453: =VLOOKUP(C3453,'products '!$A$2:$H$3072,2,0) -> Kids | P3453: =VLOOKUP(C3453,'products '!$A$2:$H$3072,3,0) -> Footwear | Q3453: =VLOOKUP(C3453,'products '!$A$2:$H$3072,4,0) -> Sandals | R3453: =VLOOKUP(C3453,'products '!$A$2:$H$3072,5,0) -> Puma | S3453: =VLOOKUP(C3453,'products '!$A$2:$H$3072,6,0) -> 6-9M | T3453: =VLOOKUP(C3453,'products '!$A$2:$H$3072,7,0) -> Grey | U3453: =VLOOKUP(C3453,'products '!$A$2:$H$3072,8,0) -> 5
A3454: OD3453 | B3454: C038 | C3454: P3053 | D3454: =RANDBETWEEN(DATE(2021,1,1),DATE(2023,3,31)) -> 44389 | E3454: =TEXT(Table1[[#This Row],[Date]],"mmm") -> Jul | F3454: =TEXT(Table1[[#This Row],[Date]],"yyyy") -> 2021 | G3454: 22365 | H3454: 0.25 | I3454: {=_xlfn.IFS(Table1[[#This Row],[Discount]]<=0.2,"Low",Table1[[#This Row],[Discount]]<=0.4,"Medium",Table1[[#This Row],[Discount]]>0.4,"High")} -> Medium | J3454: =Table1[[#This Row],[Original Price]]*(1-Table1[[#This Row],[Discount]]) -> 16773.75 | K3454: =VLOOKUP(B3454,customers!$A$2:$D$101,2,0) -> 36 | L3454: {=_xlfn.IFS(Table1[[#This Row],[Age]]<=12,"Kids",Table1[[#This Row],[Age]]<=19,"Teenage",Table1[[#This Row],[Age]]<=29,"Young Adult",Table1[[#This Row],[Age]]<=45,"Adult",Table1[[#This Row],[Age]]>=46,"Senior")} -> Adult | M3454: =VLOOKUP(B3454,customers!A$2:D$101,3,0) -> Patna | N3454: =VLOOKUP(B3454,customers!$A$2:$D$101,4,0) -> Bihar | O3454: =VLOOKUP(C3454,'products '!$A$2:$H$3072,2,0) -> Kids | P3454: =VLOOKUP(C3454,'products '!$A$2:$H$3072,3,0) -> Footwear | Q3454: =VLOOKUP(C3454,'products '!$A$2:$H$3072,4,0) -> Sandals | R3454: =VLOOKUP(C3454,'products '!$A$2:$H$3072,5,0) -> Puma | S3454: =VLOOKUP(C3454,'products '!$A$2:$H$3072,6,0) -> 9-12M | T3454: =VLOOKUP(C3454,'products '!$A$2:$H$3072,7,0) -> Black | U3454: =VLOOKUP(C3454,'products '!$A$2:$H$3072,8,0) -> 4
A3455: OD3454 | B3455: C039 | C3455: P3054 | D3455: =RANDBETWEEN(DATE(2021,1,1),DATE(2023,3,31)) -> 44448 | E3455: =TEXT(Table1[[#This Row],[Date]],"mmm") -> Sep | F3455: =TEXT(Table1[[#This Row],[Date]],"yyyy") -> 2021 | G3455: 2245 | H3455: 0.25 | I3455: {=_xlfn.IFS(Table1[[#This Row],[Discount]]<=0.2,"Low",Table1[[#This Row],[Discount]]<=0.4,"Medium",Table1[[#This Row],[Discount]]>0.4,"High")} -> Medium | J3455: =Table1[[#This Row],[Original Price]]*(1-Table1[[#This Row],[Discount]]) -> 1683.75 | K3455: =VLOOKUP(B3455,customers!$A$2:$D$101,2,0) -> 37 | L3455: {=_xlfn.IFS(Table1[[#This Row],[Age]]<=12,"Kids",Table1[[#This Row],[Age]]<=19,"Teenage",Table1[[#This Row],[Age]]<=29,"Young Adult",Table1[[#This Row],[Age]]<=45,"Adult",Table1[[#This Row],[Age]]>=46,"Senior")} -> Adult | M3455: =VLOOKUP(B3455,customers!A$2:D$101,3,0) -> Patna | N3455: =VLOOKUP(B3455,customers!$A$2:$D$101,4,0) -> Bihar | O3455: =VLOOKUP(C3455,'products '!$A$2:$H$3072,2,0) -> Kids | P3455: =VLOOKUP(C3455,'products '!$A$2:$H$3072,3,0) -> Footwear | Q3455: =VLOOKUP(C3455,'products '!$A$2:$H$3072,4,0) -> Sandals | R3455: =VLOOKUP(C3455,'products '!$A$2:$H$3072,5,0) -> Puma | S3455: =VLOOKUP(C3455,'products '!$A$2:$H$3072,6,0) -> 9-12M | T3455: =VLOOKUP(C3455,'products '!$A$2:$H$3072,7,0) -> Yellow | U3455: =VLOOKUP(C3455,'products '!$A$2:$H$3072,8,0) -> 4
A3456: OD3455 | B3456: C040 | C3456: P3054 | D3456: =RANDBETWEEN(DATE(2021,1,1),DATE(2023,3,31)) -> 44361 | E3456: =TEXT(Table1[[#This Row],[Date]],"mmm") -> Jun | F3456: =TEXT(Table1[[#This Row],[Date]],"yyyy") -> 2021 | G3456: 2245 | H3456: 0.3 | I3456: {=_xlfn.IFS(Table1[[#This Row],[Discount]]<=0.2,"Low",Table1[[#This Row],[Discount]]<=0.4,"Medium",Table1[[#This Row],[Discount]]>0.4,"High")} -> Medium | J3456: =Table1[[#This Row],[Original Price]]*(1-Table1[[#This Row],[Discount]]) -> 1571.5 | K3456: =VLOOKUP(B3456,customers!$A$2:$D$101,2,0) -> 26 | L3456: {=_xlfn.IFS(Table1[[#This Row],[Age]]<=12,"Kids",Table1[[#This Row],[Age]]<=19,"Teenage",Table1[[#This Row],[Age]]<=29,"Young Adult",Table1[[#This Row],[Age]]<=45,"Adult",Table1[[#This Row],[Age]]>=46,"Senior")} -> Young Adult | M3456: =VLOOKUP(B3456,customers!A$2:D$101,3,0) -> Patna | N3456: =VLOOKUP(B3456,customers!$A$2:$D$101,4,0) -> Bihar | O3456: =VLOOKUP(C3456,'products '!$A$2:$H$3072,2,0) -> Kids | P3456: =VLOOKUP(C3456,'products '!$A$2:$H$3072,3,0) -> Footwear | Q3456: =VLOOKUP(C3456,'products '!$A$2:$H$3072,4,0) -> Sandals | R3456: =VLOOKUP(C3456,'products '!$A$2:$H$3072,5,0) -> Puma | S3456: =VLOOKUP(C3456,'products '!$A$2:$H$3072,6,0) -> 9-12M | T3456: =VLOOKUP(C3456,'products '!$A$2:$H$3072,7,0) -> Yellow | U3456: =VLOOKUP(C3456,'products '!$A$2:$H$3072,8,0) -> 4
A3457: OD3456 | B3457: C041 | C3457: P3054 | D3457: =RANDBETWEEN(DATE(2021,1,1),DATE(2023,3,31)) -> 44652 | E3457: =TEXT(Table1[[#This Row],[Date]],"mmm") -> Apr | F3457: =TEXT(Table1[[#This Row],[Date]],"yyyy") -> 2022 | G3457: 2542 | H3457: 0.3 | I3457: {=_xlfn.IFS(Table1[[#This Row],[Discount]]<=0.2,"Low",Table1[[#This Row],[Discount]]<=0.4,"Medium",Table1[[#This Row],[Discount]]>0.4,"High")} -> Medium | J3457: =Table1[[#This Row],[Original Price]]*(1-Table1[[#This Row],[Discount]]) -> 1779.4 | K3457: =VLOOKUP(B3457,customers!$A$2:$D$101,2,0) -> 27 | L3457: {=_xlfn.IFS(Table1[[#This Row],[Age]]<=12,"Kids",Table1[[#This Row],[Age]]<=19,"Teenage",Table1[[#This Row],[Age]]<=29,"Young Adult",Table1[[#This Row],[Age]]<=45,"Adult",Table1[[#This Row],[Age]]>=46,"Senior")} -> Young Adult | M3457: =VLOOKUP(B3457,customers!A$2:D$101,3,0) -> Patna | N3457: =VLOOKUP(B3457,customers!$A$2:$D$101,4,0) -> Bihar | O3457: =VLOOKUP(C3457,'products '!$A$2:$H$3072,2,0) -> Kids | P3457: =VLOOKUP(C3457,'products '!$A$2:$H$3072,3,0) -> Footwear | Q3457: =VLOOKUP(C3457,'products '!$A$2:$H$3072,4,0) -> Sandals | R3457: =VLOOKUP(C3457,'products '!$A$2:$H$3072,5,0) -> Puma | S3457: =VLOOKUP(C3457,'products '!$A$2:$H$3072,6,0) -> 9-12M | T3457: =VLOOKUP(C3457,'products '!$A$2:$H$3072,7,0) -> Yellow | U3457: =VLOOKUP(C3457,'products '!$A$2:$H$3072,8,0) -> 4
A3458: OD3457 | B3458: C042 | C3458: P3054 | D3458: =RANDBETWEEN(DATE(2021,1,1),DATE(2023,3,31)) -> 44820 | E3458: =TEXT(Table1[[#This Row],[Date]],"mmm") -> Sep | F3458: =TEXT(Table1[[#This Row],[Date]],"yyyy") -> 2022 | G3458: 2263 | H3458: 0.3 | I3458: {=_xlfn.IFS(Table1[[#This Row],[Discount]]<=0.2,"Low",Table1[[#This Row],[Discount]]<=0.4,"Medium",Table1[[#This Row],[Discount]]>0.4,"High")} -> Medium | J3458: =Table1[[#This Row],[Original Price]]*(1-Table1[[#This Row],[Discount]]) -> 1584.1 | K3458: =VLOOKUP(B3458,customers!$A$2:$D$101,2,0) -> 28 | L3458: {=_xlfn.IFS(Table1[[#This Row],[Age]]<=12,"Kids",Table1[[#This Row],[Age]]<=19,"Teenage",Table1[[#This Row],[Age]]<=29,"Young Adult",Table1[[#This Row],[Age]]<=45,"Adult",Table1[[#This Row],[Age]]>=46,"Senior")} -> Young Adult | M3458: =VLOOKUP(B3458,customers!A$2:D$101,3,0) -> Darbhanga | N3458: =VLOOKUP(B3458,customers!$A$2:$D$101,4,0) -> Bihar | O3458: =VLOOKUP(C3458,'products '!$A$2:$H$3072,2,0) -> Kids | P3458: =VLOOKUP(C3458,'products '!$A$2:$H$3072,3,0) -> Footwear | Q3458: =VLOOKUP(C3458,'products '!$A$2:$H$3072,4,0) -> Sandals | R3458: =VLOOKUP(C3458,'products '!$A$2:$H$3072,5,0) -> Puma | S3458: =VLOOKUP(C3458,'products '!$A$2:$H$3072,6,0) -> 9-12M | T3458: =VLOOKUP(C3458,'products '!$A$2:$H$3072,7,0) -> Yellow | U3458: =VLOOKUP(C3458,'products '!$A$2:$H$3072,8,0) -> 4
A3459: OD3458 | B3459: C043 | C3459: P3054 | D3459: =RANDBETWEEN(DATE(2021,1,1),DATE(2023,3,31)) -> 44407 | E3459: =TEXT(Table1[[#This Row],[Date]],"mmm") -> Jul | F3459: =TEXT(Table1[[#This Row],[Date]],"yyyy") -> 2021 | G3459: 6523 | H3459: 0.4 | I3459: {=_xlfn.IFS(Table1[[#This Row],[Discount]]<=0.2,"Low",Table1[[#This Row],[Discount]]<=0.4,"Medium",Table1[[#This Row],[Discount]]>0.4,"High")} -> Medium | J3459: =Table1[[#This Row],[Original Price]]*(1-Table1[[#This Row],[Discount]]) -> 3913.8 | K3459: =VLOOKUP(B3459,customers!$A$2:$D$101,2,0) -> 29 | L3459: {=_xlfn.IFS(Table1[[#This Row],[Age]]<=12,"Kids",Table1[[#This Row],[Age]]<=19,"Teenage",Table1[[#This Row],[Age]]<=29,"Young Adult",Table1[[#This Row],[Age]]<=45,"Adult",Table1[[#This Row],[Age]]>=46,"Senior")} -> Young Adult | M3459: =VLOOKUP(B3459,customers!A$2:D$101,3,0) -> Darbhanga | N3459: =VLOOKUP(B3459,customers!$A$2:$D$101,4,0) -> Bihar | O3459: =VLOOKUP(C3459,'products '!$A$2:$H$3072,2,0) -> Kids | P3459: =VLOOKUP(C3459,'products '!$A$2:$H$3072,3,0) -> Footwear | Q3459: =VLOOKUP(C3459,'products '!$A$2:$H$3072,4,0) -> Sandals | R3459: =VLOOKUP(C3459,'products '!$A$2:$H$3072,5,0) -> Puma | S3459: =VLOOKUP(C3459,'products '!$A$2:$H$3072,6,0) -> 9-12M | T3459: =VLOOKUP(C3459,'products '!$A$2:$H$3072,7,0) -> Yellow | U3459: =VLOOKUP(C3459,'products '!$A$2:$H$3072,8,0) -> 4
... A3467: OD3466 | B3467: C051 | C3467: P3057 | D3467: =RANDBETWEEN(DATE(2021,1,1),DATE(2023,3,31)) -> 44242 | E3467: =TEXT(Table1[[#This Row],[Date]],"mmm") -> Feb | F3467: =TEXT(Table1[[#This Row],[Date]],"yyyy") -> 2021 | G3467: 4454 | H3467: 0.45 | I3467: {=_xlfn.IFS(Table1[[#This Row],[Discount]]<=0.2,"Low",Table1[[#This Row],[Discount]]<=0.4,"Medium",Table1[[#This Row],[Discount]]>0.4,"High")} -> High | J3467: =Table1[[#This Row],[Original Price]]*(1-Table1[[#This Row],[Discount]]) -> 2449.7 | K3467: =VLOOKUP(B3467,customers!$A$2:$D$101,2,0) -> 47 | L3467: {=_xlfn.IFS(Table1[[#This Row],[Age]]<=12,"Kids",Table1[[#This Row],[Age]]<=19,"Teenage",Table1[[#This Row],[Age]]<=29,"Young Adult",Table1[[#This Row],[Age]]<=45,"Adult",Table1[[#This Row],[Age]]>=46,"Senior")} -> Senior | M3467: =VLOOKUP(B3467,customers!A$2:D$101,3,0) -> Bhopal | N3467: =VLOOKUP(B3467,customers!$A$2:$D$101,4,0) -> Madhya Pradesh | O3467: =VLOOKUP(C3467,'products '!$A$2:$H$3072,2,0) -> Kids | P3467: =VLOOKUP(C3467,'products '!$A$2:$H$3072,3,0) -> Footwear | Q3467: =VLOOKUP(C3467,'products '!$A$2:$H$3072,4,0) -> Sandals | R3467: =VLOOKUP(C3467,'products '!$A$2:$H$3072,5,0) -> Puma | S3467: =VLOOKUP(C3467,'products '!$A$2:$H$3072,6,0) -> 9-12M | T3467: =VLOOKUP(C3467,'products '!$A$2:$H$3072,7,0) -> Yellow | U3467: =VLOOKUP(C3467,'products '!$A$2:$H$3072,8,0) -> 5
A3468: OD3467 | B3468: C052 | C3468: P3058 | D3468: =RANDBETWEEN(DATE(2021,1,1),DATE(2023,3,31)) -> 44403 | E3468: =TEXT(Table1[[#This Row],[Date]],"mmm") -> Jul | F3468: =TEXT(Table1[[#This Row],[Date]],"yyyy") -> 2021 | G3468: =RANDBETWEEN(600, 2000) -> 944 | H3468: 0.47 | I3468: {=_xlfn.IFS(Table1[[#This Row],[Discount]]<=0.2,"Low",Table1[[#This Row],[Discount]]<=0.4,"Medium",Table1[[#This Row],[Discount]]>0.4,"High")} -> High | J3468: =Table1[[#This Row],[Original Price]]*(1-Table1[[#This Row],[Discount]]) -> 500.32 | K3468: =VLOOKUP(B3468,customers!$A$2:$D$101,2,0) -> 48 | L3468: {=_xlfn.IFS(Table1[[#This Row],[Age]]<=12,"Kids",Table1[[#This Row],[Age]]<=19,"Teenage",Table1[[#This Row],[Age]]<=29,"Young Adult",Table1[[#This Row],[Age]]<=45,"Adult",Table1[[#This Row],[Age]]>=46,"Senior")} -> Senior | M3468: =VLOOKUP(B3468,customers!A$2:D$101,3,0) -> Bhopal | N3468: =VLOOKUP(B3468,customers!$A$2:$D$101,4,0) -> Madhya Pradesh | O3468: =VLOOKUP(C3468,'products '!$A$2:$H$3072,2,0) -> Kids | P3468: =VLOOKUP(C3468,'products '!$A$2:$H$3072,3,0) -> Footwear | Q3468: =VLOOKUP(C3468,'products '!$A$2:$H$3072,4,0) -> Sandals | R3468: =VLOOKUP(C3468,'products '!$A$2:$H$3072,5,0) -> Bata | S3468: =VLOOKUP(C3468,'products '!$A$2:$H$3072,6,0) -> 9-12M | T3468: =VLOOKUP(C3468,'products '!$A$2:$H$3072,7,0) -> Yellow | U3468: =VLOOKUP(C3468,'products '!$A$2:$H$3072,8,0) -> 4
A3469: OD3468 | B3469: C053 | C3469: P3059 | D3469: =RANDBETWEEN(DATE(2021,1,1),DATE(2023,3,31)) -> 44620 | E3469: =TEXT(Table1[[#This Row],[Date]],"mmm") -> Feb | F3469: =TEXT(Table1[[#This Row],[Date]],"yyyy") -> 2022 | G3469: =RANDBETWEEN(600, 2000) -> 1429 | H3469: 0.47 | I3469: {=_xlfn.IFS(Table1[[#This Row],[Discount]]<=0.2,"Low",Table1[[#This Row],[Discount]]<=0.4,"Medium",Table1[[#This Row],[Discount]]>0.4,"High")} -> High | J3469: =Table1[[#This Row],[Original Price]]*(1-Table1[[#This Row],[Discount]]) -> 757.37 | K3469: =VLOOKUP(B3469,customers!$A$2:$D$101,2,0) -> 49 | L3469: {=_xlfn.IFS(Table1[[#This Row],[Age]]<=12,"Kids",Table1[[#This Row],[Age]]<=19,"Teenage",Table1[[#This Row],[Age]]<=29,"Young Adult",Table1[[#This Row],[Age]]<=45,"Adult",Table1[[#This Row],[Age]]>=46,"Senior")} -> Senior | M3469: =VLOOKUP(B3469,customers!A$2:D$101,3,0) -> Bhopal | N3469: =VLOOKUP(B3469,customers!$A$2:$D$101,4,0) -> Madhya Pradesh | O3469: =VLOOKUP(C3469,'products '!$A$2:$H$3072,2,0) -> Kids | P3469: =VLOOKUP(C3469,'products '!$A$2:$H$3072,3,0) -> Footwear | Q3469: =VLOOKUP(C3469,'products '!$A$2:$H$3072,4,0) -> Sandals | R3469: =VLOOKUP(C3469,'products '!$A$2:$H$3072,5,0) -> Bata | S3469: =VLOOKUP(C3469,'products '!$A$2:$H$3072,6,0) -> 9-12M | T3469: =VLOOKUP(C3469,'products '!$A$2:$H$3072,7,0) -> Off white | U3469: =VLOOKUP(C3469,'products '!$A$2:$H$3072,8,0) -> 2
A3470: OD3469 | B3470: C054 | C3470: P3060 | D3470: =RANDBETWEEN(DATE(2021,1,1),DATE(2023,3,31)) -> 44529 | E3470: =TEXT(Table1[[#This Row],[Date]],"mmm") -> Nov | F3470: =TEXT(Table1[[#This Row],[Date]],"yyyy") -> 2021 | G3470: =RANDBETWEEN(600, 2000) -> 1498 | H3470: 0.46 | I3470: {=_xlfn.IFS(Table1[[#This Row],[Discount]]<=0.2,"Low",Table1[[#This Row],[Discount]]<=0.4,"Medium",Table1[[#This Row],[Discount]]>0.4,"High")} -> High | J3470: =Table1[[#This Row],[Original Price]]*(1-Table1[[#This Row],[Discount]]) -> 808.92 | K3470: =VLOOKUP(B3470,customers!$A$2:$D$101,2,0) -> 17 | L3470: {=_xlfn.IFS(Table1[[#This Row],[Age]]<=12,"Kids",Table1[[#This Row],[Age]]<=19,"Teenage",Table1[[#This Row],[Age]]<=29,"Young Adult",Table1[[#This Row],[Age]]<=45,"Adult",Table1[[#This Row],[Age]]>=46,"Senior")} -> Teenage | M3470: =VLOOKUP(B3470,customers!A$2:D$101,3,0) -> Sagar | N3470: =VLOOKUP(B3470,customers!$A$2:$D$101,4,0) -> Madhya Pradesh | O3470: =VLOOKUP(C3470,'products '!$A$2:$H$3072,2,0) -> Kids | P3470: =VLOOKUP(C3470,'products '!$A$2:$H$3072,3,0) -> Footwear | Q3470: =VLOOKUP(C3470,'products '!$A$2:$H$3072,4,0) -> Sandals | R3470: =VLOOKUP(C3470,'products '!$A$2:$H$3072,5,0) -> Bata | S3470: =VLOOKUP(C3470,'products '!$A$2:$H$3072,6,0) -> 9-12M | T3470: =VLOOKUP(C3470,'products '!$A$2:$H$3072,7,0) -> Off white | U3470: =VLOOKUP(C3470,'products '!$A$2:$H$3072,8,0) -> 5
A3471: OD3470 | B3471: C055 | C3471: P3061 | D3471: =RANDBETWEEN(DATE(2021,1,1),DATE(2023,3,31)) -> 44288 | E3471: =TEXT(Table1[[#This Row],[Date]],"mmm") -> Apr | F3471: =TEXT(Table1[[#This Row],[Date]],"yyyy") -> 2021 | G3471: =RANDBETWEEN(600, 2000) -> 1875 | H3471: 0.46 | I3471: {=_xlfn.IFS(Table1[[#This Row],[Discount]]<=0.2,"Low",Table1[[#This Row],[Discount]]<=0.4,"Medium",Table1[[#This Row],[Discount]]>0.4,"High")} -> High | J3471: =Table1[[#This Row],[Original Price]]*(1-Table1[[#This Row],[Discount]]) -> 1012.5 | K3471: =VLOOKUP(B3471,customers!$A$2:$D$101,2,0) -> 18 | L3471: {=_xlfn.IFS(Table1[[#This Row],[Age]]<=12,"Kids",Table1[[#This Row],[Age]]<=19,"Teenage",Table1[[#This Row],[Age]]<=29,"Young Adult",Table1[[#This Row],[Age]]<=45,"Adult",Table1[[#This Row],[Age]]>=46,"Senior")} -> Teenage | M3471: =VLOOKUP(B3471,customers!A$2:D$101,3,0) -> Sagar | N3471: =VLOOKUP(B3471,customers!$A$2:$D$101,4,0) -> Madhya Pradesh | O3471: =VLOOKUP(C3471,'products '!$A$2:$H$3072,2,0) -> Kids | P3471: =VLOOKUP(C3471,'products '!$A$2:$H$3072,3,0) -> Footwear | Q3471: =VLOOKUP(C3471,'products '!$A$2:$H$3072,4,0) -> Sandals | R3471: =VLOOKUP(C3471,'products '!$A$2:$H$3072,5,0) -> Bata | S3471: =VLOOKUP(C3471,'products '!$A$2:$H$3072,6,0) -> 9-12M | T3471: =VLOOKUP(C3471,'products '!$A$2:$H$3072,7,0) -> Off white | U3471: =VLOOKUP(C3471,'products '!$A$2:$H$3072,8,0) -> 5
A3472: OD3471 | B3472: C056 | C3472: P3062 | D3472: =RANDBETWEEN(DATE(2021,1,1),DATE(2023,3,31)) -> 44682 | E3472: =TEXT(Table1[[#This Row],[Date]],"mmm") -> May | F3472: =TEXT(Table1[[#This Row],[Date]],"yyyy") -> 2022 | G3472: =RANDBETWEEN(600, 2000) -> 1544 | H3472: 0.46 | I3472: {=_xlfn.IFS(Table1[[#This Row],[Discount]]<=0.2,"Low",Table1[[#This Row],[Discount]]<=0.4,"Medium",Table1[[#This Row],[Discount]]>0.4,"High")} -> High | J3472: =Table1[[#This Row],[Original Price]]*(1-Table1[[#This Row],[Discount]]) -> 833.76 | K3472: =VLOOKUP(B3472,customers!$A$2:$D$101,2,0) -> 19 | L3472: {=_xlfn.IFS(Table1[[#This Row],[Age]]<=12,"Kids",Table1[[#This Row],[Age]]<=19,"Teenage",Table1[[#This Row],[Age]]<=29,"Young Adult",Table1[[#This Row],[Age]]<=45,"Adult",Table1[[#This Row],[Age]]>=46,"Senior")} -> Teenage | M3472: =VLOOKUP(B3472,customers!A$2:D$101,3,0) -> Sagar | N3472: =VLOOKUP(B3472,customers!$A$2:$D$101,4,0) -> Madhya Pradesh | O3472: =VLOOKUP(C3472,'products '!$A$2:$H$3072,2,0) -> Kids | P3472: =VLOOKUP(C3472,'products '!$A$2:$H$3072,3,0) -> Footwear | Q3472: =VLOOKUP(C3472,'products '!$A$2:$H$3072,4,0) -> Sandals | R3472: =VLOOKUP(C3472,'products '!$A$2:$H$3072,5,0) -> Bata | S3472: =VLOOKUP(C3472,'products '!$A$2:$H$3072,6,0) -> 9-12M | T3472: =VLOOKUP(C3472,'products '!$A$2:$H$3072,7,0) -> Cream | U3472: =VLOOKUP(C3472,'products '!$A$2:$H$3072,8,0) -> 5
A3473: OD3472 | B3473: C057 | C3473: P3063 | D3473: =RANDBETWEEN(DATE(2021,1,1),DATE(2023,3,31)) -> 44724 | E3473: =TEXT(Table1[[#This Row],[Date]],"mmm") -> Jun | F3473: =TEXT(Table1[[#This Row],[Date]],"yyyy") -> 2022 | G3473: =RANDBETWEEN(600, 2000) -> 934 | H3473: 0.3 | I3473: {=_xlfn.IFS(Table1[[#This Row],[Discount]]<=0.2,"Low",Table1[[#This Row],[Discount]]<=0.4,"Medium",Table1[[#This Row],[Discount]]>0.4,"High")} -> Medium | J3473: =Table1[[#This Row],[Original Price]]*(1-Table1[[#This Row],[Discount]]) -> 653.8 | K3473: =VLOOKUP(B3473,customers!$A$2:$D$101,2,0) -> 20 | L3473: {=_xlfn.IFS(Table1[[#This Row],[Age]]<=12,"Kids",Table1[[#This Row],[Age]]<=19,"Teenage",Table1[[#This Row],[Age]]<=29,"Young Adult",Table1[[#This Row],[Age]]<=45,"Adult",Table1[[#This Row],[Age]]>=46,"Senior")} -> Young Adult | M3473: =VLOOKUP(B3473,customers!A$2:D$101,3,0) -> Sagar | N3473: =VLOOKUP(B3473,customers!$A$2:$D$101,4,0) -> Madhya Pradesh | O3473: =VLOOKUP(C3473,'products '!$A$2:$H$3072,2,0) -> Kids | P3473: =VLOOKUP(C3473,'products '!$A$2:$H$3072,3,0) -> Footwear | Q3473: =VLOOKUP(C3473,'products '!$A$2:$H$3072,4,0) -> Sandals | R3473: =VLOOKUP(C3473,'products '!$A$2:$H$3072,5,0) -> Bata | S3473: =VLOOKUP(C3473,'products '!$A$2:$H$3072,6,0) -> 9-12M | T3473: =VLOOKUP(C3473,'products '!$A$2:$H$3072,7,0) -> Cream | U3473: =VLOOKUP(C3473,'products '!$A$2:$H$3072,8,0) -> 4
A3474: OD3473 | B3474: C058 | C3474: P3064 | D3474: =RANDBETWEEN(DATE(2021,1,1),DATE(2023,3,31)) -> 44981 | E3474: =TEXT(Table1[[#This Row],[Date]],"mmm") -> Feb | F3474: =TEXT(Table1[[#This Row],[Date]],"yyyy") -> 2023 | G3474: =RANDBETWEEN(600, 2000) -> 1004 | H3474: 0.3 | I3474: {=_xlfn.IFS(Table1[[#This Row],[Discount]]<=0.2,"Low",Table1[[#This Row],[Discount]]<=0.4,"Medium",Table1[[#This Row],[Discount]]>0.4,"High")} -> Medium | J3474: =Table1[[#This Row],[Original Price]]*(1-Table1[[#This Row],[Discount]]) -> 702.8 | K3474: =VLOOKUP(B3474,customers!$A$2:$D$101,2,0) -> 21 | L3474: {=_xlfn.IFS(Table1[[#This Row],[Age]]<=12,"Kids",Table1[[#This Row],[Age]]<=19,"Teenage",Table1[[#This Row],[Age]]<=29,"Young Adult",Table1[[#This Row],[Age]]<=45,"Adult",Table1[[#This Row],[Age]]>=46,"Senior")} -> Young Adult | M3474: =VLOOKUP(B3474,customers!A$2:D$101,3,0) -> Indore | N3474: =VLOOKUP(B3474,customers!$A$2:$D$101,4,0) -> Madhya Pradesh | O3474: =VLOOKUP(C3474,'products '!$A$2:$H$3072,2,0) -> Kids | P3474: =VLOOKUP(C3474,'products '!$A$2:$H$3072,3,0) -> Footwear | Q3474: =VLOOKUP(C3474,'products '!$A$2:$H$3072,4,0) -> Sandals | R3474: =VLOOKUP(C3474,'products '!$A$2:$H$3072,5,0) -> Bata | S3474: =VLOOKUP(C3474,'products '!$A$2:$H$3072,6,0) -> 9-12M | T3474: =VLOOKUP(C3474,'products '!$A$2:$H$3072,7,0) -> Cream | U3474: =VLOOKUP(C3474,'products '!$A$2:$H$3072,8,0) -> 4
A3475: OD3474 | B3475: C059 | C3475: P3065 | D3475: =RANDBETWEEN(DATE(2021,1,1),DATE(2023,3,31)) -> 44880 | E3475: =TEXT(Table1[[#This Row],[Date]],"mmm") -> Nov | F3475: =TEXT(Table1[[#This Row],[Date]],"yyyy") -> 2022 | G3475: =RANDBETWEEN(600, 2000) -> 1281 | H3475: 0.3 | I3475: {=_xlfn.IFS(Table1[[#This Row],[Discount]]<=0.2,"Low",Table1[[#This Row],[Discount]]<=0.4,"Medium",Table1[[#This Row],[Discount]]>0.4,"High")} -> Medium | J3475: =Table1[[#This Row],[Original Price]]*(1-Table1[[#This Row],[Discount]]) -> 896.7 | K3475: =VLOOKUP(B3475,customers!$A$2:$D$101,2,0) -> 22 | L3475: {=_xlfn.IFS(Table1[[#This Row],[Age]]<=12,"Kids",Table1[[#This Row],[Age]]<=19,"Teenage",Table1[[#This Row],[Age]]<=29,"Young Adult",Table1[[#This Row],[Age]]<=45,"Adult",Table1[[#This Row],[Age]]>=46,"Senior")} -> Young Adult | M3475: =VLOOKUP(B3475,customers!A$2:D$101,3,0) -> Indore | N3475: =VLOOKUP(B3475,customers!$A$2:$D$101,4,0) -> Madhya Pradesh | O3475: =VLOOKUP(C3475,'products '!$A$2:$H$3072,2,0) -> Kids | P3475: =VLOOKUP(C3475,'products '!$A$2:$H$3072,3,0) -> Footwear | Q3475: =VLOOKUP(C3475,'products '!$A$2:$H$3072,4,0) -> Sandals | R3475: =VLOOKUP(C3475,'products '!$A$2:$H$3072,5,0) -> Campus | S3475: =VLOOKUP(C3475,'products '!$A$2:$H$3072,6,0) -> 9-12M | T3475: =VLOOKUP(C3475,'products '!$A$2:$H$3072,7,0) -> Mustard | U3475: =VLOOKUP(C3475,'products '!$A$2:$H$3072,8,0) -> 4
A3476: OD3475 | B3476: C060 | C3476: P3066 | D3476: =RANDBETWEEN(DATE(2021,1,1),DATE(2023,3,31)) -> 44926 | E3476: =TEXT(Table1[[#This Row],[Date]],"mmm") -> Dec | F3476: =TEXT(Table1[[#This Row],[Date]],"yyyy") -> 2022 | G3476: =RANDBETWEEN(600, 2000) -> 1604 | H3476: 0.3 | I3476: {=_xlfn.IFS(Table1[[#This Row],[Discount]]<=0.2,"Low",Table1[[#This Row],[Discount]]<=0.4,"Medium",Table1[[#This Row],[Discount]]>0.4,"High")} -> Medium | J3476: =Table1[[#This Row],[Original Price]]*(1-Table1[[#This Row],[Discount]]) -> 1122.8 | K3476: =VLOOKUP(B3476,customers!$A$2:$D$101,2,0) -> 16 | L3476: {=_xlfn.IFS(Table1[[#This Row],[Age]]<=12,"Kids",Table1[[#This Row],[Age]]<=19,"Teenage",Table1[[#This Row],[Age]]<=29,"Young Adult",Table1[[#This Row],[Age]]<=45,"Adult",Table1[[#This Row],[Age]]>=46,"Senior")} -> Teenage | M3476: =VLOOKUP(B3476,customers!A$2:D$101,3,0) -> Kanpur | N3476: =VLOOKUP(B3476,customers!$A$2:$D$101,4,0) -> Uttar Pradesh | O3476: =VLOOKUP(C3476,'products '!$A$2:$H$3072,2,0) -> Kids | P3476: =VLOOKUP(C3476,'products '!$A$2:$H$3072,3,0) -> Footwear | Q3476: =VLOOKUP(C3476,'products '!$A$2:$H$3072,4,0) -> Sandals | R3476: =VLOOKUP(C3476,'products '!$A$2:$H$3072,5,0) -> Campus | S3476: =VLOOKUP(C3476,'products '!$A$2:$H$3072,6,0) -> 9-12M | T3476: =VLOOKUP(C3476,'products '!$A$2:$H$3072,7,0) -> Mustard | U3476: =VLOOKUP(C3476,'products '!$A$2:$H$3072,8,0) -> 5
A3477: OD3476 | B3477: C061 | C3477: P3067 | D3477: =RANDBETWEEN(DATE(2021,1,1),DATE(2023,3,31)) -> 44886 | E3477: =TEXT(Table1[[#This Row],[Date]],"mmm") -> Nov | F3477: =TEXT(Table1[[#This Row],[Date]],"yyyy") -> 2022 | G3477: =RANDBETWEEN(600, 2000) -> 1854 | H3477: 0.3 | I3477: {=_xlfn.IFS(Table1[[#This Row],[Discount]]<=0.2,"Low",Table1[[#This Row],[Discount]]<=0.4,"Medium",Table1[[#This Row],[Discount]]>0.4,"High")} -> Medium | J3477: =Table1[[#This Row],[Original Price]]*(1-Table1[[#This Row],[Discount]]) -> 1297.8 | K3477: =VLOOKUP(B3477,customers!$A$2:$D$101,2,0) -> 17 | L3477: {=_xlfn.IFS(Table1[[#This Row],[Age]]<=12,"Kids",Table1[[#This Row],[Age]]<=19,"Teenage",Table1[[#This Row],[Age]]<=29,"Young Adult",Table1[[#This Row],[Age]]<=45,"Adult",Table1[[#This Row],[Age]]>=46,"Senior")} -> Teenage | M3477: =VLOOKUP(B3477,customers!A$2:D$101,3,0) -> Kanpur | N3477: =VLOOKUP(B3477,customers!$A$2:$D$101,4,0) -> Uttar Pradesh | O3477: =VLOOKUP(C3477,'products '!$A$2:$H$3072,2,0) -> Kids | P3477: =VLOOKUP(C3477,'products '!$A$2:$H$3072,3,0) -> Footwear | Q3477: =VLOOKUP(C3477,'products '!$A$2:$H$3072,4,0) -> Sandals | R3477: =VLOOKUP(C3477,'products '!$A$2:$H$3072,5,0) -> Campus | S3477: =VLOOKUP(C3477,'products '!$A$2:$H$3072,6,0) -> 9-12M | T3477: =VLOOKUP(C3477,'products '!$A$2:$H$3072,7,0) -> Olive | U3477: =VLOOKUP(C3477,'products '!$A$2:$H$3072,8,0) -> 5
A3478: OD3477 | B3478: C062 | C3478: P3068 | D3478: =RANDBETWEEN(DATE(2021,1,1),DATE(2023,3,31)) -> 44667 | E3478: =TEXT(Table1[[#This Row],[Date]],"mmm") -> Apr | F3478: =TEXT(Table1[[#This Row],[Date]],"yyyy") -> 2022 | G3478: =RANDBETWEEN(600, 2000) -> 783 | H3478: 0.35 | I3478: {=_xlfn.IFS(Table1[[#This Row],[Discount]]<=0.2,"Low",Table1[[#This Row],[Discount]]<=0.4,"Medium",Table1[[#This Row],[Discount]]>0.4,"High")} -> Medium | J3478: =Table1[[#This Row],[Original Price]]*(1-Table1[[#This Row],[Discount]]) -> 508.95 | K3478: =VLOOKUP(B3478,customers!$A$2:$D$101,2,0) -> 18 | L3478: {=_xlfn.IFS(Table1[[#This Row],[Age]]<=12,"Kids",Table1[[#This Row],[Age]]<=19,"Teenage",Table1[[#This Row],[Age]]<=29,"Young Adult",Table1[[#This Row],[Age]]<=45,"Adult",Table1[[#This Row],[Age]]>=46,"Senior")} -> Teenage | M3478: =VLOOKUP(B3478,customers!A$2:D$101,3,0) -> Kanpur | N3478: =VLOOKUP(B3478,customers!$A$2:$D$101,4,0) -> Uttar Pradesh | O3478: =VLOOKUP(C3478,'products '!$A$2:$H$3072,2,0) -> Kids | P3478: =VLOOKUP(C3478,'products '!$A$2:$H$3072,3,0) -> Footwear | Q3478: =VLOOKUP(C3478,'products '!$A$2:$H$3072,4,0) -> Sandals | R3478: =VLOOKUP(C3478,'products '!$A$2:$H$3072,5,0) -> Campus | S3478: =VLOOKUP(C3478,'products '!$A$2:$H$3072,6,0) -> 9-12M | T3478: =VLOOKUP(C3478,'products '!$A$2:$H$3072,7,0) -> Teal | U3478: =VLOOKUP(C3478,'products '!$A$2:$H$3072,8,0) -> 3
A3479: OD3478 | B3479: C063 | C3479: P3068 | D3479: =RANDBETWEEN(DATE(2021,1,1),DATE(2023,3,31)) -> 44826 | E3479: =TEXT(Table1[[#This Row],[Date]],"mmm") -> Sep | F3479: =TEXT(Table1[[#This Row],[Date]],"yyyy") -> 2022 | G3479: =RANDBETWEEN(600, 2000) -> 1337 | H3479: 0.35 | I3479: {=_xlfn.IFS(Table1[[#This Row],[Discount]]<=0.2,"Low",Table1[[#This Row],[Discount]]<=0.4,"Medium",Table1[[#This Row],[Discount]]>0.4,"High")} -> Medium | J3479: =Table1[[#This Row],[Original Price]]*(1-Table1[[#This Row],[Discount]]) -> 869.05 | K3479: =VLOOKUP(B3479,customers!$A$2:$D$101,2,0) -> 19 | L3479: {=_xlfn.IFS(Table1[[#This Row],[Age]]<=12,"Kids",Table1[[#This Row],[Age]]<=19,"Teenage",Table1[[#This Row],[Age]]<=29,"Young Adult",Table1[[#This Row],[Age]]<=45,"Adult",Table1[[#This Row],[Age]]>=46,"Senior")} -> Teenage | M3479: =VLOOKUP(B3479,customers!A$2:D$101,3,0) -> Kanpur | N3479: =VLOOKUP(B3479,customers!$A$2:$D$101,4,0) -> Uttar Pradesh | O3479: =VLOOKUP(C3479,'products '!$A$2:$H$3072,2,0) -> Kids | P3479: =VLOOKUP(C3479,'products '!$A$2:$H$3072,3,0) -> Footwear | Q3479: =VLOOKUP(C3479,'products '!$A$2:$H$3072,4,0) -> Sandals | R3479: =VLOOKUP(C3479,'products '!$A$2:$H$3072,5,0) -> Campus | S3479: =VLOOKUP(C3479,'products '!$A$2:$H$3072,6,0) -> 9-12M | T3479: =VLOOKUP(C3479,'products '!$A$2:$H$3072,7,0) -> Teal | U3479: =VLOOKUP(C3479,'products '!$A$2:$H$3072,8,0) -> 3
... A3501: OD3500 | B3501: C085 | C3501: P3071 | D3501: =RANDBETWEEN(DATE(2021,1,1),DATE(2023,3,31)) -> 44246 | E3501: =TEXT(Table1[[#This Row],[Date]],"mmm") -> Feb | F3501: =TEXT(Table1[[#This Row],[Date]],"yyyy") -> 2021 | G3501: =RANDBETWEEN(600, 2000) -> 756 | H3501: 0.5 | I3501: {=_xlfn.IFS(Table1[[#This Row],[Discount]]<=0.2,"Low",Table1[[#This Row],[Discount]]<=0.4,"Medium",Table1[[#This Row],[Discount]]>0.4,"High")} -> High | J3501: =Table1[[#This Row],[Original Price]]*(1-Table1[[#This Row],[Discount]]) -> 378 | K3501: =VLOOKUP(B3501,customers!$A$2:$D$101,2,0) -> 24 | L3501: {=_xlfn.IFS(Table1[[#This Row],[Age]]<=12,"Kids",Table1[[#This Row],[Age]]<=19,"Teenage",Table1[[#This Row],[Age]]<=29,"Young Adult",Table1[[#This Row],[Age]]<=45,"Adult",Table1[[#This Row],[Age]]>=46,"Senior")} -> Young Adult | M3501: =VLOOKUP(B3501,customers!A$2:D$101,3,0) -> Patiala | N3501: =VLOOKUP(B3501,customers!$A$2:$D$101,4,0) -> Punjab | O3501: =VLOOKUP(C3501,'products '!$A$2:$H$3072,2,0) -> Kids | P3501: =VLOOKUP(C3501,'products '!$A$2:$H$3072,3,0) -> Footwear | Q3501: =VLOOKUP(C3501,'products '!$A$2:$H$3072,4,0) -> Sandals | R3501: =VLOOKUP(C3501,'products '!$A$2:$H$3072,5,0) -> Campus | S3501: =VLOOKUP(C3501,'products '!$A$2:$H$3072,6,0) -> 3-6M | T3501: =VLOOKUP(C3501,'products '!$A$2:$H$3072,7,0) -> Charcoal | U3501: =VLOOKUP(C3501,'products '!$A$2:$H$3072,8,0) -> 4
A3503: Avg Rating | B3503: =AVERAGE(Table1[Ratings]) -> 3.9777143
A3504: Total orders | B3504: =COUNTA(Table1[Order ID]) -> 3500
A3505: Avg order value | B3505: =SUM(Table1[Revenue])/COUNTA(Table1[Order ID]) -> 536.48598
A3506: avg discount | B3506: =AVERAGE(Table1[Discount]) -> 0.35514571
A3508: Total Revenue | B3508: =SUM(Table1[Revenue]) -> 1877700.9

Sheet Resources
A2: 2.Top States by Customer Spend | E2: 3. Sub-category Performance | H2: 5.Brand Affinity (Customer preference) | P2: colors | Q2: Position | R2: Angle | S2: Transparency | U2: Shadow | V2: 0.2 | W2: 100 | X2: 35 | Y2: 135 | Z2: 15
E3: Sum of Revenue | H3: Sum of Revenue | P3: #12143D | U3: Shadow | V3: 0.2 | W3: 100 | X3: 35 | Y3: 135 | Z3: 8
A4: Sum of Revenue | E4: Sub-category | F4: Total | H4: Brand Name | I4: Total | P4: #1F2357 | Q4: 0 | R4: 135 | U4: Shadow | V4: 0.2 | W4: 100 | X4: 15 | Y4: 135 | Z4: 15
A5: State | B5: Total | E5: Bottomwear | F5: 231736.22 | H5: Adidas | I5: 72145 | P5: #10123B | Q5: 75 | R5: 135
A6: Bihar | B6: 233321.87 | E6: Boys Clothing | F6: 54148.56 | H6: Allen Solly | I6: 56416.28 | O6: Line | P6: #4647A6 | Q6: 0 | R6: 135
A7: Chhatisgarh | B7: 38283.83 | E7: Footwear | F7: 387938.1 | H7: DressBerry | I7: 45183.63 | O7: Line | P7: #333787 | Q7: 100 | R7: 135
A8: Gujrat | B8: 299839.15 | E8: Girls Clothing | F8: 159213.72 | H8: H&M | I8: 162482.14
A9: Karnataka | B9: 153376.54 | E9: Haircare | F9: 71399.57 | H9: Here&Now | I9: 77711.52 | P9: #20245A | Q9: 0 | R9: 135
A10: Madhya Pradesh | B10: 189578.09 | E10: Indian & Fusion Wear | F10: 163235.35 | H10: HRX by Hrithik Roshan | I10: 62324.5 | P10: #10123B | Q10: 75 | R10: 135
A11: Maharashtra | B11: 158985.27 | E11: Infants | F11: 74138 | H11: Puma | I11: 248787.15 | O11: Line | P11: #B9C1FF | Q11: 0 | R11: 150
A12: Punjab | B12: 251507.73 | E12: Makeup | F12: 169989.93 | H12: Red Tape | I12: 53995.65 | O12: Line | P12: #3D4098 | Q12: 33 | R12: 150
A13: Rajasthan | B13: 211694.54 | E13: Skincare | F13: 70626.86 | H13: Roadster | I13: 120210.12 | O13: Line | P13: #333787 | Q13: 100 | R13: 150
A14: Telangana | B14: 80145.61 | E14: Topwear | F14: 306136.85 | H14: Wrogn | I14: 55902.71
A15: Uttar Pradesh | B15: 265220.58 | E15: Western Wear | F15: 193390.05 | H15: Grand Total | I15: 955158.7 | P15: #323687 | Q15: 0 | R15: 110
A16: Grand Total | B16: 1881953.2 | E16: Grand Total | F16: 1881953.2 | P16: #10123A | Q16: 75 | R16: 110
O17: Line | P17: #A2D8F0 | Q17: 0 | R17: 135
A18: 7. Revenue by Age Group | O18: Line | P18: #5D63D1 | Q18: 38 | R18: 135
E19: 4.Discount Sensitivity | O19: Line | P19: #2E327A | Q19: 100 | R19: 135
A20: Sum of Revenue
A21: Age Group | B21: Total | E21: Count of Order ID | P21: #CEC5FF
A22: Adult | B22: 480128.67 | E22: Discount Group | F22: Total | P22: #6372A4
A23: Senior | B23: 75182.28 | E23: High | F23: 922 | P23: #05075F1
A24: Teenage | B24: 411725.96 | E24: Low | F24: 293
A25: Young Adult | B25: 914916.3 | E25: Medium | F25: 2285 | O25: slicer | P25: #2069F0
A26: Grand Total | B26: 1881953.2 | E26: Grand Total | F26: 3500 | P26: #9933FF
P27: WHOLE
A29: 1.Customer Activity Trend
A30: Sum of Revenue
A31: Months (Date) | B31: Total
A32: Jan | B32: 224812.91
A33: Feb | B33: 195838.29
A34: Mar | B34: 228426.52
A35: Apr | B35: 136437.38
A36: May | B36: 140000.25
A37: Jun | B37: 134355.54
A38: Jul | B38: 136060.46
A39: Aug | B39: 146739.71 | E39: 6.Ratings Distribution
A40: Sep | B40: 134047.62
A41: Oct | B41: 130682.32 | E41: Count of Order ID
A42: Nov | B42: 141560.51 | E42: Ratings | F42: Total
A43: Dec | B43: 132991.7 | E43: 2 | F43: 382
A44: Grand Total | B44: 1881953.2 | E44: 3 | F44: 571
E45: 4 | F45: 1290
E46: 5 | F46: 1257
E47: Grand Total | F47: 3500

Sheet Dashboard
F2: #VALUE!
